{
"meta":{"test_sets":[],"test_metrics":[],"learn_metrics":[{"best_value":"Min","name":"Logloss"}],"launch_mode":"Train","parameters":"","iteration_count":1000,"learn_sets":["learn"],"name":"experiment"},
"iterations":[
{"learn":[0.6800353073],"iteration":0,"passed_time":0.1605912967,"remaining_time":160.4307054},
{"learn":[0.6671741674],"iteration":1,"passed_time":0.1709876584,"remaining_time":85.32284157},
{"learn":[0.6527810342],"iteration":2,"passed_time":0.1908318019,"remaining_time":63.41976883},
{"learn":[0.6413539181],"iteration":3,"passed_time":0.1987798894,"remaining_time":49.49619246},
{"learn":[0.6296683463],"iteration":4,"passed_time":0.2046003512,"remaining_time":40.71546989},
{"learn":[0.6189523778],"iteration":5,"passed_time":0.2112137038,"remaining_time":34.99107027},
{"learn":[0.6091647714],"iteration":6,"passed_time":0.2164899142,"remaining_time":30.71064068},
{"learn":[0.5989962685],"iteration":7,"passed_time":0.2229020882,"remaining_time":27.63985894},
{"learn":[0.5896334423],"iteration":8,"passed_time":0.2283282805,"remaining_time":25.14148066},
{"learn":[0.58117756],"iteration":9,"passed_time":0.2338245368,"remaining_time":23.14862914},
{"learn":[0.5736359831],"iteration":10,"passed_time":0.2402109632,"remaining_time":21.59714933},
{"learn":[0.5660469482],"iteration":11,"passed_time":0.2457921125,"remaining_time":20.23688393},
{"learn":[0.5589498363],"iteration":12,"passed_time":0.2514492401,"remaining_time":19.0908},
{"learn":[0.55273357],"iteration":13,"passed_time":0.2572832789,"remaining_time":18.12009378},
{"learn":[0.5463323233],"iteration":14,"passed_time":0.2628134414,"remaining_time":17.25808265},
{"learn":[0.5398453394],"iteration":15,"passed_time":0.2689104691,"remaining_time":16.53799385},
{"learn":[0.5336812163],"iteration":16,"passed_time":0.2749386545,"remaining_time":15.89792337},
{"learn":[0.5281061726],"iteration":17,"passed_time":0.2801328743,"remaining_time":15.28280459},
{"learn":[0.5228766018],"iteration":18,"passed_time":0.2862421415,"remaining_time":14.77913372},
{"learn":[0.5177136008],"iteration":19,"passed_time":0.2922317702,"remaining_time":14.31935674},
{"learn":[0.5128509964],"iteration":20,"passed_time":0.2978160405,"remaining_time":13.88390018},
{"learn":[0.5080495083],"iteration":21,"passed_time":0.3036531016,"remaining_time":13.49876061},
{"learn":[0.5037352587],"iteration":22,"passed_time":0.3100990297,"remaining_time":13.17246748},
{"learn":[0.4995790543],"iteration":23,"passed_time":0.3162344695,"remaining_time":12.86020176},
{"learn":[0.4957528761],"iteration":24,"passed_time":0.3218818444,"remaining_time":12.55339193},
{"learn":[0.4916744605],"iteration":25,"passed_time":0.3281465661,"remaining_time":12.29287521},
{"learn":[0.4880041816],"iteration":26,"passed_time":0.3334833214,"remaining_time":12.0177508},
{"learn":[0.4842544394],"iteration":27,"passed_time":0.3388509935,"remaining_time":11.7629702},
{"learn":[0.4814012455],"iteration":28,"passed_time":0.34443217,"remaining_time":11.53253921},
{"learn":[0.4780825246],"iteration":29,"passed_time":0.3498544098,"remaining_time":11.31195925},
{"learn":[0.4754030382],"iteration":30,"passed_time":0.3562843618,"remaining_time":11.13675957},
{"learn":[0.4727711988],"iteration":31,"passed_time":0.3623460489,"remaining_time":10.96096798},
{"learn":[0.4703660649],"iteration":32,"passed_time":0.3681204662,"remaining_time":10.78704518},
{"learn":[0.4680161906],"iteration":33,"passed_time":0.3740475342,"remaining_time":10.62735053},
{"learn":[0.4657800561],"iteration":34,"passed_time":0.3797153801,"remaining_time":10.46929548},
{"learn":[0.4633986599],"iteration":35,"passed_time":0.3854679802,"remaining_time":10.32197591},
{"learn":[0.4610394323],"iteration":36,"passed_time":0.3911064943,"remaining_time":10.1793393},
{"learn":[0.4591893246],"iteration":37,"passed_time":0.3978388838,"remaining_time":10.07160543},
{"learn":[0.4575391711],"iteration":38,"passed_time":0.4041970445,"remaining_time":9.959829737},
{"learn":[0.4553754966],"iteration":39,"passed_time":0.4107727154,"remaining_time":9.858545169},
{"learn":[0.4535894977],"iteration":40,"passed_time":0.4159996671,"remaining_time":9.730333677},
{"learn":[0.451802755],"iteration":41,"passed_time":0.421758712,"remaining_time":9.620115384},
{"learn":[0.4500199104],"iteration":42,"passed_time":0.4270776131,"remaining_time":9.504959901},
{"learn":[0.4484217536],"iteration":43,"passed_time":0.4325018053,"remaining_time":9.397084679},
{"learn":[0.4466234948],"iteration":44,"passed_time":0.4381465619,"remaining_time":9.298443703},
{"learn":[0.4451171224],"iteration":45,"passed_time":0.4434200395,"remaining_time":9.196146037},
{"learn":[0.4437175804],"iteration":46,"passed_time":0.4489303807,"remaining_time":9.102779846},
{"learn":[0.4423463745],"iteration":47,"passed_time":0.4542840719,"remaining_time":9.009967426},
{"learn":[0.441062715],"iteration":48,"passed_time":0.4584760862,"remaining_time":8.898178733},
{"learn":[0.439875581],"iteration":49,"passed_time":0.4638897433,"remaining_time":8.813905122},
{"learn":[0.4387139463],"iteration":50,"passed_time":0.4692255503,"remaining_time":8.731275435},
{"learn":[0.4375699794],"iteration":51,"passed_time":0.4744415801,"remaining_time":8.64943496},
{"learn":[0.4364219818],"iteration":52,"passed_time":0.4799527703,"remaining_time":8.575759877},
{"learn":[0.4352984946],"iteration":53,"passed_time":0.485538319,"remaining_time":8.505912033},
{"learn":[0.4341493079],"iteration":54,"passed_time":0.490925264,"remaining_time":8.434988627},
{"learn":[0.4332682251],"iteration":55,"passed_time":0.4963242323,"remaining_time":8.366608487},
{"learn":[0.432332013],"iteration":56,"passed_time":0.5016807183,"remaining_time":8.299735392},
{"learn":[0.4311103108],"iteration":57,"passed_time":0.5070239246,"remaining_time":8.234767878},
{"learn":[0.4301406813],"iteration":58,"passed_time":0.5123034696,"remaining_time":8.170806185},
{"learn":[0.4292070383],"iteration":59,"passed_time":0.5180552555,"remaining_time":8.116199003},
{"learn":[0.4281805826],"iteration":60,"passed_time":0.5239138422,"remaining_time":8.06483767},
{"learn":[0.4275589372],"iteration":61,"passed_time":0.5289806901,"remaining_time":8.002965924},
{"learn":[0.4267108823],"iteration":62,"passed_time":0.5357843289,"remaining_time":7.968728829},
{"learn":[0.425744609],"iteration":63,"passed_time":0.5425210639,"remaining_time":7.93437056},
{"learn":[0.4249902933],"iteration":64,"passed_time":0.548541104,"remaining_time":7.890552803},
{"learn":[0.4242152659],"iteration":65,"passed_time":0.5546200566,"remaining_time":7.848714135},
{"learn":[0.423235961],"iteration":66,"passed_time":0.5602617633,"remaining_time":7.801854107},
{"learn":[0.4224836658],"iteration":67,"passed_time":0.565931998,"remaining_time":7.756597385},
{"learn":[0.4217690614],"iteration":68,"passed_time":0.5718500168,"remaining_time":7.715831386},
{"learn":[0.4210276627],"iteration":69,"passed_time":0.577171416,"remaining_time":7.668134526},
{"learn":[0.4206078379],"iteration":70,"passed_time":0.5810299999,"remaining_time":7.602491125},
{"learn":[0.4199432271],"iteration":71,"passed_time":0.5870981432,"remaining_time":7.567042735},
{"learn":[0.4193107698],"iteration":72,"passed_time":0.5930133029,"remaining_time":7.530456599},
{"learn":[0.4187353583],"iteration":73,"passed_time":0.5981785544,"remaining_time":7.485315424},
{"learn":[0.4180351342],"iteration":74,"passed_time":0.6037141752,"remaining_time":7.445808161},
{"learn":[0.4173633619],"iteration":75,"passed_time":0.6092758504,"remaining_time":7.407511655},
{"learn":[0.4167249748],"iteration":76,"passed_time":0.6146685872,"remaining_time":7.368040337},
{"learn":[0.4160141847],"iteration":77,"passed_time":0.6201572992,"remaining_time":7.330577306},
{"learn":[0.4155836907],"iteration":78,"passed_time":0.6256027547,"remaining_time":7.293419456},
{"learn":[0.4148769442],"iteration":79,"passed_time":0.6312357355,"remaining_time":7.259210959},
{"learn":[0.4142707567],"iteration":80,"passed_time":0.6366477379,"remaining_time":7.223200878},
{"learn":[0.4138346696],"iteration":81,"passed_time":0.6424868734,"remaining_time":7.1927189},
{"learn":[0.413263334],"iteration":82,"passed_time":0.6481984366,"remaining_time":7.161421281},
{"learn":[0.4127297726],"iteration":83,"passed_time":0.6538201511,"remaining_time":7.129753076},
{"learn":[0.4122391916],"iteration":84,"passed_time":0.6595968942,"remaining_time":7.100366567},
{"learn":[0.4117516287],"iteration":85,"passed_time":0.6651091153,"remaining_time":7.068717806},
{"learn":[0.4114137549],"iteration":86,"passed_time":0.6705773214,"remaining_time":7.037207982},
{"learn":[0.4111191882],"iteration":87,"passed_time":0.6765539409,"remaining_time":7.011559024},
{"learn":[0.4106378582],"iteration":88,"passed_time":0.68278301,"remaining_time":6.988936203},
{"learn":[0.4102085885],"iteration":89,"passed_time":0.6886174012,"remaining_time":6.962687057},
{"learn":[0.4098072661],"iteration":90,"passed_time":0.6958165842,"remaining_time":6.950519506},
{"learn":[0.4093135386],"iteration":91,"passed_time":0.7056820057,"remaining_time":6.964774578},
{"learn":[0.4089707586],"iteration":92,"passed_time":0.7130561145,"remaining_time":6.954213934},
{"learn":[0.4086200416],"iteration":93,"passed_time":0.7213235016,"remaining_time":6.95233077},
{"learn":[0.4081986537],"iteration":94,"passed_time":0.7295217892,"remaining_time":6.949654939},
{"learn":[0.4077380333],"iteration":95,"passed_time":0.7369037022,"remaining_time":6.939176529},
{"learn":[0.4072481039],"iteration":96,"passed_time":0.7436570874,"remaining_time":6.922910824},
{"learn":[0.4069661486],"iteration":97,"passed_time":0.7496876525,"remaining_time":6.900186353},
{"learn":[0.4065387364],"iteration":98,"passed_time":0.7573305788,"remaining_time":6.892473247},
{"learn":[0.4062123152],"iteration":99,"passed_time":0.763330517,"remaining_time":6.869974653},
{"learn":[0.4057447676],"iteration":100,"passed_time":0.7696646206,"remaining_time":6.850777167},
{"learn":[0.405498092],"iteration":101,"passed_time":0.7753327169,"remaining_time":6.825968429},
{"learn":[0.4051887409],"iteration":102,"passed_time":0.7809423861,"remaining_time":6.801022528},
{"learn":[0.4047463094],"iteration":103,"passed_time":0.7886574337,"remaining_time":6.794587121},
{"learn":[0.4044595726],"iteration":104,"passed_time":0.7963607838,"remaining_time":6.788027633},
{"learn":[0.4041542466],"iteration":105,"passed_time":0.8037370533,"remaining_time":6.778687978},
{"learn":[0.4038675534],"iteration":106,"passed_time":0.811237552,"remaining_time":6.770421812},
{"learn":[0.4034989931],"iteration":107,"passed_time":0.8180545917,"remaining_time":6.756524961},
{"learn":[0.4031696941],"iteration":108,"passed_time":0.8235698899,"remaining_time":6.732117174},
{"learn":[0.402880503],"iteration":109,"passed_time":0.8292523908,"remaining_time":6.709405707},
{"learn":[0.4025729927],"iteration":110,"passed_time":0.8351373299,"remaining_time":6.688622399},
{"learn":[0.4022827694],"iteration":111,"passed_time":0.8406411958,"remaining_time":6.665083767},
{"learn":[0.4020050263],"iteration":112,"passed_time":0.8471418109,"remaining_time":6.649688374},
{"learn":[0.4016534666],"iteration":113,"passed_time":0.8528976799,"remaining_time":6.628660916},
{"learn":[0.4013453862],"iteration":114,"passed_time":0.8582992526,"remaining_time":6.605172509},
{"learn":[0.4011143274],"iteration":115,"passed_time":0.8654137643,"remaining_time":6.595049721},
{"learn":[0.400870889],"iteration":116,"passed_time":0.8716150171,"remaining_time":6.578085984},
{"learn":[0.4005998424],"iteration":117,"passed_time":0.8788428188,"remaining_time":6.568977679},
{"learn":[0.4003089997],"iteration":118,"passed_time":0.8862632802,"remaining_time":6.56132731},
{"learn":[0.4000561699],"iteration":119,"passed_time":0.8935284908,"remaining_time":6.552542266},
{"learn":[0.3997562722],"iteration":120,"passed_time":0.8994622831,"remaining_time":6.534110305},
{"learn":[0.3995343721],"iteration":121,"passed_time":0.9058277734,"remaining_time":6.518990042},
{"learn":[0.3992866705],"iteration":122,"passed_time":0.913534389,"remaining_time":6.513574465},
{"learn":[0.3989787683],"iteration":123,"passed_time":0.9207135494,"remaining_time":6.50439572},
{"learn":[0.3987246925],"iteration":124,"passed_time":0.9291965925,"remaining_time":6.504376148},
{"learn":[0.3984273978],"iteration":125,"passed_time":0.9365803458,"remaining_time":6.496597002},
{"learn":[0.3982632129],"iteration":126,"passed_time":0.9422905466,"remaining_time":6.477320057},
{"learn":[0.3980580144],"iteration":127,"passed_time":0.948061976,"remaining_time":6.458672211},
{"learn":[0.3978728858],"iteration":128,"passed_time":0.9547493708,"remaining_time":6.446408542},
{"learn":[0.3978108932],"iteration":129,"passed_time":0.9594733704,"remaining_time":6.421091017},
{"learn":[0.3976462547],"iteration":130,"passed_time":0.9665129231,"remaining_time":6.411448322},
{"learn":[0.3975558644],"iteration":131,"passed_time":0.9723848039,"remaining_time":6.394166741},
{"learn":[0.3973023628],"iteration":132,"passed_time":0.978667262,"remaining_time":6.379733204},
{"learn":[0.3970593631],"iteration":133,"passed_time":0.9855548837,"remaining_time":6.369332308},
{"learn":[0.3968528109],"iteration":134,"passed_time":0.9918789693,"remaining_time":6.355372655},
{"learn":[0.3965523977],"iteration":135,"passed_time":0.9985527844,"remaining_time":6.343747101},
{"learn":[0.3963314586],"iteration":136,"passed_time":1.004853471,"remaining_time":6.329843398},
{"learn":[0.3960993554],"iteration":137,"passed_time":1.011714238,"remaining_time":6.319548357},
{"learn":[0.3957517148],"iteration":138,"passed_time":1.018886674,"remaining_time":6.311233281},
{"learn":[0.395588825],"iteration":139,"passed_time":1.026000941,"remaining_time":6.30257721},
{"learn":[0.3952743151],"iteration":140,"passed_time":1.033197973,"remaining_time":6.294447225},
{"learn":[0.3950501899],"iteration":141,"passed_time":1.03897424,"remaining_time":6.27774576},
{"learn":[0.3948616581],"iteration":142,"passed_time":1.045176843,"remaining_time":6.263752129},
{"learn":[0.3946335337],"iteration":143,"passed_time":1.050738331,"remaining_time":6.246055633},
{"learn":[0.3943613598],"iteration":144,"passed_time":1.05751656,"remaining_time":6.235701094},
{"learn":[0.3940465492],"iteration":145,"passed_time":1.064037227,"remaining_time":6.223888986},
{"learn":[0.3938636698],"iteration":146,"passed_time":1.069696322,"remaining_time":6.207149405},
{"learn":[0.3936772269],"iteration":147,"passed_time":1.075866092,"remaining_time":6.193499394},
{"learn":[0.3934776257],"iteration":148,"passed_time":1.082262517,"remaining_time":6.181244308},
{"learn":[0.393207675],"iteration":149,"passed_time":1.088090647,"remaining_time":6.165847002},
{"learn":[0.3930290923],"iteration":150,"passed_time":1.093615349,"remaining_time":6.148870405},
{"learn":[0.3929035452],"iteration":151,"passed_time":1.09906814,"remaining_time":6.131643305},
{"learn":[0.3927241865],"iteration":152,"passed_time":1.105255139,"remaining_time":6.118634659},
{"learn":[0.3924781989],"iteration":153,"passed_time":1.110733686,"remaining_time":6.101822715},
{"learn":[0.3922460148],"iteration":154,"passed_time":1.116219579,"remaining_time":6.08519706},
{"learn":[0.3920629378],"iteration":155,"passed_time":1.121462789,"remaining_time":6.067401245},
{"learn":[0.3918693871],"iteration":156,"passed_time":1.127164453,"remaining_time":6.052226966},
{"learn":[0.3917020083],"iteration":157,"passed_time":1.132482904,"remaining_time":6.035130413},
{"learn":[0.3915941358],"iteration":158,"passed_time":1.137793671,"remaining_time":6.018141368},
{"learn":[0.3914186704],"iteration":159,"passed_time":1.143199952,"remaining_time":6.001799748},
{"learn":[0.3911548714],"iteration":160,"passed_time":1.148536884,"remaining_time":5.985232581},
{"learn":[0.3908920736],"iteration":161,"passed_time":1.154150417,"remaining_time":5.970234875},
{"learn":[0.3907658609],"iteration":162,"passed_time":1.159585618,"remaining_time":5.954436579},
{"learn":[0.3905073576],"iteration":163,"passed_time":1.165365044,"remaining_time":5.940519371},
{"learn":[0.3902969662],"iteration":164,"passed_time":1.170991959,"remaining_time":5.925929006},
{"learn":[0.3900588534],"iteration":165,"passed_time":1.176607897,"remaining_time":5.911391482},
{"learn":[0.3898596216],"iteration":166,"passed_time":1.182448827,"remaining_time":5.898083073},
{"learn":[0.3895848316],"iteration":167,"passed_time":1.188059214,"remaining_time":5.883721819},
{"learn":[0.3893894425],"iteration":168,"passed_time":1.193703132,"remaining_time":5.869629008},
{"learn":[0.3892218143],"iteration":169,"passed_time":1.199459115,"remaining_time":5.856182736},
{"learn":[0.3890949952],"iteration":170,"passed_time":1.20522559,"remaining_time":5.842877277},
{"learn":[0.3889780027],"iteration":171,"passed_time":1.211243985,"remaining_time":5.830872205},
{"learn":[0.3888709038],"iteration":172,"passed_time":1.216924044,"remaining_time":5.817318986},
{"learn":[0.3886764591],"iteration":173,"passed_time":1.222804008,"remaining_time":5.804805234},
{"learn":[0.3885166389],"iteration":174,"passed_time":1.229528323,"remaining_time":5.796347808},
{"learn":[0.3883455675],"iteration":175,"passed_time":1.235242179,"remaining_time":5.783179293},
{"learn":[0.388191774],"iteration":176,"passed_time":1.241160709,"remaining_time":5.771046685},
{"learn":[0.3880917164],"iteration":177,"passed_time":1.247639501,"remaining_time":5.761571179},
{"learn":[0.3879026059],"iteration":178,"passed_time":1.254345968,"remaining_time":5.753173408},
{"learn":[0.38773011],"iteration":179,"passed_time":1.260764174,"remaining_time":5.743481237},
{"learn":[0.3875455148],"iteration":180,"passed_time":1.267139317,"remaining_time":5.73363039},
{"learn":[0.3873832154],"iteration":181,"passed_time":1.273202826,"remaining_time":5.722417098},
{"learn":[0.3872116462],"iteration":182,"passed_time":1.281079195,"remaining_time":5.719353563},
{"learn":[0.3870462749],"iteration":183,"passed_time":1.287289041,"remaining_time":5.708847051},
{"learn":[0.3868343117],"iteration":184,"passed_time":1.294730767,"remaining_time":5.703813918},
{"learn":[0.3866826343],"iteration":185,"passed_time":1.302447316,"remaining_time":5.69995761},
{"learn":[0.38648372],"iteration":186,"passed_time":1.308999936,"remaining_time":5.690999722},
{"learn":[0.3863431428],"iteration":187,"passed_time":1.315293469,"remaining_time":5.680948386},
{"learn":[0.3861023039],"iteration":188,"passed_time":1.323158344,"remaining_time":5.677679454},
{"learn":[0.3859194357],"iteration":189,"passed_time":1.331118962,"remaining_time":5.67477031},
{"learn":[0.3857339385],"iteration":190,"passed_time":1.340487324,"remaining_time":5.677770918},
{"learn":[0.3855775491],"iteration":191,"passed_time":1.347962399,"remaining_time":5.672675096},
{"learn":[0.3853902626],"iteration":192,"passed_time":1.354475932,"remaining_time":5.663534078},
{"learn":[0.3852810051],"iteration":193,"passed_time":1.361303952,"remaining_time":5.655726729},
{"learn":[0.3850639392],"iteration":194,"passed_time":1.368257787,"remaining_time":5.648448812},
{"learn":[0.3848338205],"iteration":195,"passed_time":1.375975935,"remaining_time":5.644309447},
{"learn":[0.3847296944],"iteration":196,"passed_time":1.384196968,"remaining_time":5.642183579},
{"learn":[0.3845580868],"iteration":197,"passed_time":1.394706837,"remaining_time":5.649267087},
{"learn":[0.3844057456],"iteration":198,"passed_time":1.411270516,"remaining_time":5.680541123},
{"learn":[0.38428172],"iteration":199,"passed_time":1.420825051,"remaining_time":5.683300205},
{"learn":[0.3841830419],"iteration":200,"passed_time":1.429894488,"remaining_time":5.684008438},
{"learn":[0.3840463563],"iteration":201,"passed_time":1.438069975,"remaining_time":5.681088316},
{"learn":[0.3838460648],"iteration":202,"passed_time":1.445470669,"remaining_time":5.675074497},
{"learn":[0.3837531789],"iteration":203,"passed_time":1.453920646,"remaining_time":5.673141342},
{"learn":[0.3835714307],"iteration":204,"passed_time":1.462393113,"remaining_time":5.671231827},
{"learn":[0.3832957708],"iteration":205,"passed_time":1.471343566,"remaining_time":5.671100929},
{"learn":[0.3831514331],"iteration":206,"passed_time":1.478142604,"remaining_time":5.662642921},
{"learn":[0.3829481832],"iteration":207,"passed_time":1.486393751,"remaining_time":5.659730053},
{"learn":[0.3827344411],"iteration":208,"passed_time":1.492263257,"remaining_time":5.647752329},
{"learn":[0.3825669056],"iteration":209,"passed_time":1.513928552,"remaining_time":5.695255028},
{"learn":[0.3824360081],"iteration":210,"passed_time":1.52176022,"remaining_time":5.690373524},
{"learn":[0.3822563921],"iteration":211,"passed_time":1.528752285,"remaining_time":5.682343399},
{"learn":[0.3819696136],"iteration":212,"passed_time":1.536828649,"remaining_time":5.678329327},
{"learn":[0.3818435268],"iteration":213,"passed_time":1.54336951,"remaining_time":5.668637548},
{"learn":[0.3817597294],"iteration":214,"passed_time":1.550128651,"remaining_time":5.65977205},
{"learn":[0.3815510295],"iteration":215,"passed_time":1.55807869,"remaining_time":5.655248577},
{"learn":[0.3814001907],"iteration":216,"passed_time":1.567023393,"remaining_time":5.654282566},
{"learn":[0.3811882692],"iteration":217,"passed_time":1.574557075,"remaining_time":5.648181799},
{"learn":[0.3809940745],"iteration":218,"passed_time":1.582924986,"remaining_time":5.645042985},
{"learn":[0.3808424357],"iteration":219,"passed_time":1.589838654,"remaining_time":5.636700683},
{"learn":[0.3806851999],"iteration":220,"passed_time":1.595960663,"remaining_time":5.6255808},
{"learn":[0.3805436961],"iteration":221,"passed_time":1.6026082,"remaining_time":5.616347655},
{"learn":[0.3804205203],"iteration":222,"passed_time":1.610660634,"remaining_time":5.612032792},
{"learn":[0.3803435522],"iteration":223,"passed_time":1.6166916,"remaining_time":5.600681614},
{"learn":[0.3802087784],"iteration":224,"passed_time":1.623960798,"remaining_time":5.593642749},
{"learn":[0.3800211375],"iteration":225,"passed_time":1.62997117,"remaining_time":5.582290643},
{"learn":[0.3798805208],"iteration":226,"passed_time":1.636944187,"remaining_time":5.574263685},
{"learn":[0.3797916311],"iteration":227,"passed_time":1.643623481,"remaining_time":5.565251437},
{"learn":[0.3796631418],"iteration":228,"passed_time":1.649783916,"remaining_time":5.554512662},
{"learn":[0.3795270339],"iteration":229,"passed_time":1.655911824,"remaining_time":5.543704803},
{"learn":[0.3793931411],"iteration":230,"passed_time":1.66186162,"remaining_time":5.532344528},
{"learn":[0.3791887398],"iteration":231,"passed_time":1.667605668,"remaining_time":5.520349796},
{"learn":[0.3790661013],"iteration":232,"passed_time":1.673390709,"remaining_time":5.508543665},
{"learn":[0.3788890698],"iteration":233,"passed_time":1.679515196,"remaining_time":5.497900171},
{"learn":[0.3787405243],"iteration":234,"passed_time":1.685230731,"remaining_time":5.485963869},
{"learn":[0.3786370446],"iteration":235,"passed_time":1.690993173,"remaining_time":5.474232136},
{"learn":[0.3785253516],"iteration":236,"passed_time":1.696672488,"remaining_time":5.462283158},
{"learn":[0.3784199382],"iteration":237,"passed_time":1.702106163,"remaining_time":5.449600403},
{"learn":[0.3782274266],"iteration":238,"passed_time":1.70755222,"remaining_time":5.437017739},
{"learn":[0.3781200557],"iteration":239,"passed_time":1.713084289,"remaining_time":5.424766915},
{"learn":[0.3780689593],"iteration":240,"passed_time":1.718924274,"remaining_time":5.413541593},
{"learn":[0.377918955],"iteration":241,"passed_time":1.725117596,"remaining_time":5.403467511},
{"learn":[0.3777091857],"iteration":242,"passed_time":1.730565566,"remaining_time":5.391103429},
{"learn":[0.3776045455],"iteration":243,"passed_time":1.73624386,"remaining_time":5.379509666},
{"learn":[0.3774772036],"iteration":244,"passed_time":1.742268755,"remaining_time":5.369032285},
{"learn":[0.3772331241],"iteration":245,"passed_time":1.748115687,"remaining_time":5.358045642},
{"learn":[0.3770414554],"iteration":246,"passed_time":1.75497615,"remaining_time":5.35019045},
{"learn":[0.3769103693],"iteration":247,"passed_time":1.761257942,"remaining_time":5.340588598},
{"learn":[0.3768302033],"iteration":248,"passed_time":1.76723437,"remaining_time":5.330092417},
{"learn":[0.3766289807],"iteration":249,"passed_time":1.775035598,"remaining_time":5.325106793},
{"learn":[0.3764837438],"iteration":250,"passed_time":1.780926257,"remaining_time":5.314397475},
{"learn":[0.3763538358],"iteration":251,"passed_time":1.787007723,"remaining_time":5.304292767},
{"learn":[0.3762050647],"iteration":252,"passed_time":1.793194493,"remaining_time":5.294530774},
{"learn":[0.3760928609],"iteration":253,"passed_time":1.79914044,"remaining_time":5.284089638},
{"learn":[0.376025017],"iteration":254,"passed_time":1.805306966,"remaining_time":5.274328196},
{"learn":[0.3759239324],"iteration":255,"passed_time":1.811437783,"remaining_time":5.264491057},
{"learn":[0.3757974353],"iteration":256,"passed_time":1.817696601,"remaining_time":5.255052819},
{"learn":[0.3756396908],"iteration":257,"passed_time":1.823741427,"remaining_time":5.245023795},
{"learn":[0.3754907069],"iteration":258,"passed_time":1.829384342,"remaining_time":5.233875665},
{"learn":[0.3753363651],"iteration":259,"passed_time":1.835008522,"remaining_time":5.222716564},
{"learn":[0.3752514999],"iteration":260,"passed_time":1.840589,"remaining_time":5.211476133},
{"learn":[0.3750181368],"iteration":261,"passed_time":1.846259465,"remaining_time":5.200532385},
{"learn":[0.3749301441],"iteration":262,"passed_time":1.851839066,"remaining_time":5.189374112},
{"learn":[0.3747610327],"iteration":263,"passed_time":1.857610658,"remaining_time":5.17879335},
{"learn":[0.3746150381],"iteration":264,"passed_time":1.863150286,"remaining_time":5.16760551},
{"learn":[0.3744696568],"iteration":265,"passed_time":1.868885058,"remaining_time":5.15699862},
{"learn":[0.3742369911],"iteration":266,"passed_time":1.874471495,"remaining_time":5.146020995},
{"learn":[0.3741723155],"iteration":267,"passed_time":1.880466196,"remaining_time":5.136198714},
{"learn":[0.3740632085],"iteration":268,"passed_time":1.886116055,"remaining_time":5.125467793},
{"learn":[0.3739598698],"iteration":269,"passed_time":1.892454085,"remaining_time":5.116635118},
{"learn":[0.3737624153],"iteration":270,"passed_time":1.898758907,"remaining_time":5.107731524},
{"learn":[0.3735951213],"iteration":271,"passed_time":1.904354813,"remaining_time":5.096949647},
{"learn":[0.3733858332],"iteration":272,"passed_time":1.910932726,"remaining_time":5.088820849},
{"learn":[0.3732661954],"iteration":273,"passed_time":1.917336503,"remaining_time":5.080241976},
{"learn":[0.3730955538],"iteration":274,"passed_time":1.924274455,"remaining_time":5.073087201},
{"learn":[0.3729346671],"iteration":275,"passed_time":1.930432694,"remaining_time":5.063888661},
{"learn":[0.3728035596],"iteration":276,"passed_time":1.937475309,"remaining_time":5.05702039},
{"learn":[0.3726606522],"iteration":277,"passed_time":1.944107026,"remaining_time":5.049083715},
{"learn":[0.3725508367],"iteration":278,"passed_time":1.949993944,"remaining_time":5.039231661},
{"learn":[0.3723877672],"iteration":279,"passed_time":1.956301094,"remaining_time":5.030488527},
{"learn":[0.3723159737],"iteration":280,"passed_time":1.961797185,"remaining_time":5.019687459},
{"learn":[0.3721360424],"iteration":281,"passed_time":1.968241104,"remaining_time":5.011337279},
{"learn":[0.3719948948],"iteration":282,"passed_time":1.974355027,"remaining_time":5.002164502},
{"learn":[0.3718800633],"iteration":283,"passed_time":1.980109109,"remaining_time":4.992106064},
{"learn":[0.3717376378],"iteration":284,"passed_time":1.98606139,"remaining_time":4.982575067},
{"learn":[0.3715973592],"iteration":285,"passed_time":1.991859837,"remaining_time":4.972685049},
{"learn":[0.371564721],"iteration":286,"passed_time":1.996446211,"remaining_time":4.959812364},
{"learn":[0.371502259],"iteration":287,"passed_time":2.002870863,"remaining_time":4.951541855},
{"learn":[0.3714319571],"iteration":288,"passed_time":2.009107931,"remaining_time":4.942822627},
{"learn":[0.3714089124],"iteration":289,"passed_time":2.014596623,"remaining_time":4.932288285},
{"learn":[0.3711957755],"iteration":290,"passed_time":2.021142021,"remaining_time":4.924363205},
{"learn":[0.371017386],"iteration":291,"passed_time":2.027601731,"remaining_time":4.916239815},
{"learn":[0.3709152892],"iteration":292,"passed_time":2.034064444,"remaining_time":4.908135023},
{"learn":[0.3708435862],"iteration":293,"passed_time":2.040124523,"remaining_time":4.899074536},
{"learn":[0.3707264819],"iteration":294,"passed_time":2.046980185,"remaining_time":4.891935696},
{"learn":[0.3706396262],"iteration":295,"passed_time":2.053063778,"remaining_time":4.882962499},
{"learn":[0.3704720152],"iteration":296,"passed_time":2.06000381,"remaining_time":4.876035954},
{"learn":[0.3703960901],"iteration":297,"passed_time":2.066656549,"remaining_time":4.868432542},
{"learn":[0.3702734147],"iteration":298,"passed_time":2.072971302,"remaining_time":4.860043087},
{"learn":[0.3701098763],"iteration":299,"passed_time":2.079997495,"remaining_time":4.853327489},
{"learn":[0.3700162485],"iteration":300,"passed_time":2.085902368,"remaining_time":4.844005832},
{"learn":[0.369906473],"iteration":301,"passed_time":2.094390029,"remaining_time":4.840676293},
{"learn":[0.3697732195],"iteration":302,"passed_time":2.101983933,"remaining_time":4.83525677},
{"learn":[0.3696336217],"iteration":303,"passed_time":2.11050824,"remaining_time":4.831953076},
{"learn":[0.3694281309],"iteration":304,"passed_time":2.117677481,"remaining_time":4.825527375},
{"learn":[0.3692677295],"iteration":305,"passed_time":2.127314873,"remaining_time":4.824694515},
{"learn":[0.3691817376],"iteration":306,"passed_time":2.136979357,"remaining_time":4.823865454},
{"learn":[0.3690160484],"iteration":307,"passed_time":2.145339288,"remaining_time":4.82004801},
{"learn":[0.3689039216],"iteration":308,"passed_time":2.154429011,"remaining_time":4.817833161},
{"learn":[0.3688393994],"iteration":309,"passed_time":2.161969855,"remaining_time":4.812126451},
{"learn":[0.3687388553],"iteration":310,"passed_time":2.169683271,"remaining_time":4.806790269},
{"learn":[0.3686224728],"iteration":311,"passed_time":2.175425507,"remaining_time":4.797092144},
{"learn":[0.3685118817],"iteration":312,"passed_time":2.182859839,"remaining_time":4.791133258},
{"learn":[0.3684530524],"iteration":313,"passed_time":2.189081881,"remaining_time":4.782516466},
{"learn":[0.3683363399],"iteration":314,"passed_time":2.195113644,"remaining_time":4.773501098},
{"learn":[0.3681932227],"iteration":315,"passed_time":2.201007634,"remaining_time":4.764206399},
{"learn":[0.3680571514],"iteration":316,"passed_time":2.206675852,"remaining_time":4.754446709},
{"learn":[0.3680531543],"iteration":317,"passed_time":2.211767993,"remaining_time":4.743477269},
{"learn":[0.3678861401],"iteration":318,"passed_time":2.218069207,"remaining_time":4.735125799},
{"learn":[0.3677587712],"iteration":319,"passed_time":2.223655999,"remaining_time":4.725268998},
{"learn":[0.3676156367],"iteration":320,"passed_time":2.230180903,"remaining_time":4.717423157},
{"learn":[0.3674876438],"iteration":321,"passed_time":2.235581554,"remaining_time":4.707218304},
{"learn":[0.3673788967],"iteration":322,"passed_time":2.241470643,"remaining_time":4.698066952},
{"learn":[0.3673728093],"iteration":323,"passed_time":2.245770882,"remaining_time":4.685620728},
{"learn":[0.3671080223],"iteration":324,"passed_time":2.251530087,"remaining_time":4.676254795},
{"learn":[0.3668605123],"iteration":325,"passed_time":2.257504785,"remaining_time":4.667356518},
{"learn":[0.3667370876],"iteration":326,"passed_time":2.264476991,"remaining_time":4.660529097},
{"learn":[0.3666508391],"iteration":327,"passed_time":2.270649275,"remaining_time":4.652061929},
{"learn":[0.3665219229],"iteration":328,"passed_time":2.276658892,"remaining_time":4.643276951},
{"learn":[0.3663698811],"iteration":329,"passed_time":2.282566669,"remaining_time":4.634302025},
{"learn":[0.3662496763],"iteration":330,"passed_time":2.288466928,"remaining_time":4.625330438},
{"learn":[0.3661620233],"iteration":331,"passed_time":2.293936346,"remaining_time":4.61551048},
{"learn":[0.3660558728],"iteration":332,"passed_time":2.300084756,"remaining_time":4.607076674},
{"learn":[0.365934857],"iteration":333,"passed_time":2.305953668,"remaining_time":4.598099231},
{"learn":[0.3658352411],"iteration":334,"passed_time":2.311283318,"remaining_time":4.588069871},
{"learn":[0.3656850656],"iteration":335,"passed_time":2.316701997,"remaining_time":4.578244422},
{"learn":[0.3655408028],"iteration":336,"passed_time":2.322229497,"remaining_time":4.568659219},
{"learn":[0.3654491499],"iteration":337,"passed_time":2.32751912,"remaining_time":4.558632122},
{"learn":[0.3653787969],"iteration":338,"passed_time":2.33314205,"remaining_time":4.549282876},
{"learn":[0.365164624],"iteration":339,"passed_time":2.338523318,"remaining_time":4.539486441},
{"learn":[0.365046589],"iteration":340,"passed_time":2.343808101,"remaining_time":4.529529439},
{"learn":[0.3649077663],"iteration":341,"passed_time":2.349594996,"remaining_time":4.520565811},
{"learn":[0.3648448142],"iteration":342,"passed_time":2.355457598,"remaining_time":4.51176572},
{"learn":[0.3646277339],"iteration":343,"passed_time":2.361307615,"remaining_time":4.502958708},
{"learn":[0.3645723866],"iteration":344,"passed_time":2.366761064,"remaining_time":4.493415933},
{"learn":[0.3645143611],"iteration":345,"passed_time":2.372105429,"remaining_time":4.483690609},
{"learn":[0.3643930659],"iteration":346,"passed_time":2.378137788,"remaining_time":4.475285232},
{"learn":[0.3642212391],"iteration":347,"passed_time":2.3837872,"remaining_time":4.466176019},
{"learn":[0.3641063362],"iteration":348,"passed_time":2.389178265,"remaining_time":4.456604729},
{"learn":[0.3640356083],"iteration":349,"passed_time":2.395270754,"remaining_time":4.448359971},
{"learn":[0.363866829],"iteration":350,"passed_time":2.40042748,"remaining_time":4.438397249},
{"learn":[0.3636836759],"iteration":351,"passed_time":2.405707969,"remaining_time":4.42868967},
{"learn":[0.3636154899],"iteration":352,"passed_time":2.411058583,"remaining_time":4.419135704},
{"learn":[0.3634510172],"iteration":353,"passed_time":2.416752523,"remaining_time":4.410232004},
{"learn":[0.3633164779],"iteration":354,"passed_time":2.422177004,"remaining_time":4.400856811},
{"learn":[0.3631952527],"iteration":355,"passed_time":2.427546753,"remaining_time":4.3914048},
{"learn":[0.3631154453],"iteration":356,"passed_time":2.433891918,"remaining_time":4.383732502},
{"learn":[0.363017881],"iteration":357,"passed_time":2.440392726,"remaining_time":4.376346732},
{"learn":[0.3628915049],"iteration":358,"passed_time":2.446179946,"remaining_time":4.367691771},
{"learn":[0.3627562686],"iteration":359,"passed_time":2.452205709,"remaining_time":4.359476816},
{"learn":[0.362642344],"iteration":360,"passed_time":2.458719431,"remaining_time":4.352137718},
{"learn":[0.3624676877],"iteration":361,"passed_time":2.465133126,"remaining_time":4.34462689},
{"learn":[0.3622565165],"iteration":362,"passed_time":2.472160996,"remaining_time":4.338199875},
{"learn":[0.3621638408],"iteration":363,"passed_time":2.478558504,"remaining_time":4.330668155},
{"learn":[0.3620647582],"iteration":364,"passed_time":2.485460681,"remaining_time":4.324020636},
{"learn":[0.3620642426],"iteration":365,"passed_time":2.489703481,"remaining_time":4.312765047},
{"learn":[0.3619503684],"iteration":366,"passed_time":2.495366884,"remaining_time":4.303997923},
{"learn":[0.36180439],"iteration":367,"passed_time":2.502071063,"remaining_time":4.297035086},
{"learn":[0.3616656632],"iteration":368,"passed_time":2.508019102,"remaining_time":4.288780632},
{"learn":[0.3614977157],"iteration":369,"passed_time":2.514544513,"remaining_time":4.281521739},
{"learn":[0.3613750274],"iteration":370,"passed_time":2.52061212,"remaining_time":4.273490629},
{"learn":[0.3612495006],"iteration":371,"passed_time":2.526441879,"remaining_time":4.265068548},
{"learn":[0.3611109232],"iteration":372,"passed_time":2.532925012,"remaining_time":4.257758667},
{"learn":[0.3609988647],"iteration":373,"passed_time":2.538890505,"remaining_time":4.249586781},
{"learn":[0.3609159391],"iteration":374,"passed_time":2.54562077,"remaining_time":4.242701283},
{"learn":[0.3607492028],"iteration":375,"passed_time":2.551483459,"remaining_time":4.234376803},
{"learn":[0.3606141199],"iteration":376,"passed_time":2.557772851,"remaining_time":4.22677052},
{"learn":[0.3604825698],"iteration":377,"passed_time":2.564281517,"remaining_time":4.219532019},
{"learn":[0.3604003402],"iteration":378,"passed_time":2.57001923,"remaining_time":4.211034147},
{"learn":[0.3603273741],"iteration":379,"passed_time":2.57640577,"remaining_time":4.203609415},
{"learn":[0.3602329056],"iteration":380,"passed_time":2.582084042,"remaining_time":4.195039427},
{"learn":[0.360109561],"iteration":381,"passed_time":2.587631924,"remaining_time":4.186273637},
{"learn":[0.3599383245],"iteration":382,"passed_time":2.59322033,"remaining_time":4.177589932},
{"learn":[0.3597887981],"iteration":383,"passed_time":2.598730328,"remaining_time":4.168796567},
{"learn":[0.3596915273],"iteration":384,"passed_time":2.605970159,"remaining_time":4.1627835},
{"learn":[0.3595923736],"iteration":385,"passed_time":2.611819639,"remaining_time":4.154552482},
{"learn":[0.3594249372],"iteration":386,"passed_time":2.617643772,"remaining_time":4.146293623},
{"learn":[0.3592907361],"iteration":387,"passed_time":2.623685498,"remaining_time":4.138390528},
{"learn":[0.3591482395],"iteration":388,"passed_time":2.629696929,"remaining_time":4.130449419},
{"learn":[0.3590776581],"iteration":389,"passed_time":2.636910265,"remaining_time":4.124398106},
{"learn":[0.3589084317],"iteration":390,"passed_time":2.642271415,"remaining_time":4.115455989},
{"learn":[0.3587750593],"iteration":391,"passed_time":2.647747218,"remaining_time":4.10670997},
{"learn":[0.3586874412],"iteration":392,"passed_time":2.653483811,"remaining_time":4.098383392},
{"learn":[0.3585294563],"iteration":393,"passed_time":2.658618359,"remaining_time":4.089143973},
{"learn":[0.3583467884],"iteration":394,"passed_time":2.664202561,"remaining_time":4.08061405},
{"learn":[0.3581333383],"iteration":395,"passed_time":2.669519036,"remaining_time":4.071690652},
{"learn":[0.3580070949],"iteration":396,"passed_time":2.674695942,"remaining_time":4.062573433},
{"learn":[0.357907209],"iteration":397,"passed_time":2.680280074,"remaining_time":4.054091971},
{"learn":[0.3577637561],"iteration":398,"passed_time":2.685727397,"remaining_time":4.045418961},
{"learn":[0.357671673],"iteration":399,"passed_time":2.69092447,"remaining_time":4.036386705},
{"learn":[0.3574525173],"iteration":400,"passed_time":2.696169676,"remaining_time":4.027445476},
{"learn":[0.3574173773],"iteration":401,"passed_time":2.701297373,"remaining_time":4.018347833},
{"learn":[0.3572353778],"iteration":402,"passed_time":2.707131952,"remaining_time":4.010317061},
{"learn":[0.3571673376],"iteration":403,"passed_time":2.712856297,"remaining_time":4.002134537},
{"learn":[0.3570964505],"iteration":404,"passed_time":2.719005746,"remaining_time":3.994588689},
{"learn":[0.3569476334],"iteration":405,"passed_time":2.725057722,"remaining_time":3.98690711},
{"learn":[0.3568091079],"iteration":406,"passed_time":2.730838684,"remaining_time":3.978838672},
{"learn":[0.3566965176],"iteration":407,"passed_time":2.73645567,"remaining_time":3.970543521},
{"learn":[0.3566299366],"iteration":408,"passed_time":2.742010767,"remaining_time":3.962172038},
{"learn":[0.3564850771],"iteration":409,"passed_time":2.74756296,"remaining_time":3.953810114},
{"learn":[0.3563970586],"iteration":410,"passed_time":2.752863718,"remaining_time":3.945101532},
{"learn":[0.3563071471],"iteration":411,"passed_time":2.758359214,"remaining_time":3.936687422},
{"learn":[0.3561762729],"iteration":412,"passed_time":2.763849809,"remaining_time":3.928280479},
{"learn":[0.3560623289],"iteration":413,"passed_time":2.769108708,"remaining_time":3.919559669},
{"learn":[0.355944111],"iteration":414,"passed_time":2.775782526,"remaining_time":3.912850067},
{"learn":[0.3558185837],"iteration":415,"passed_time":2.781414886,"remaining_time":3.904678591},
{"learn":[0.3557244834],"iteration":416,"passed_time":2.787886696,"remaining_time":3.89769291},
{"learn":[0.3555601526],"iteration":417,"passed_time":2.793175256,"remaining_time":3.889062199},
{"learn":[0.3554622738],"iteration":418,"passed_time":2.798668862,"remaining_time":3.880731763},
{"learn":[0.3552742081],"iteration":419,"passed_time":2.804756503,"remaining_time":3.873235171},
{"learn":[0.3551737942],"iteration":420,"passed_time":2.810689017,"remaining_time":3.865531927},
{"learn":[0.3549831975],"iteration":421,"passed_time":2.816721885,"remaining_time":3.857974526},
{"learn":[0.3548870393],"iteration":422,"passed_time":2.822158338,"remaining_time":3.849610782},
{"learn":[0.3547818946],"iteration":423,"passed_time":2.827435018,"remaining_time":3.841043798},
{"learn":[0.3546770546],"iteration":424,"passed_time":2.833000114,"remaining_time":3.832882507},
{"learn":[0.3545732422],"iteration":425,"passed_time":2.838558207,"remaining_time":3.824723969},
{"learn":[0.3544543004],"iteration":426,"passed_time":2.843962965,"remaining_time":3.816371848},
{"learn":[0.3542556895],"iteration":427,"passed_time":2.849509015,"remaining_time":3.808222328},
{"learn":[0.3541593499],"iteration":428,"passed_time":2.855024326,"remaining_time":3.800044033},
{"learn":[0.3540373871],"iteration":429,"passed_time":2.861801303,"remaining_time":3.793550564},
{"learn":[0.3539106849],"iteration":430,"passed_time":2.867761437,"remaining_time":3.785977396},
{"learn":[0.3538175364],"iteration":431,"passed_time":2.873821831,"remaining_time":3.778543518},
{"learn":[0.3537288133],"iteration":432,"passed_time":2.880662683,"remaining_time":3.772137971},
{"learn":[0.3535222866],"iteration":433,"passed_time":2.887476519,"remaining_time":3.765695184},
{"learn":[0.353432068],"iteration":434,"passed_time":2.895471015,"remaining_time":3.760784192},
{"learn":[0.3533197143],"iteration":435,"passed_time":2.902716154,"remaining_time":3.754889703},
{"learn":[0.3532138212],"iteration":436,"passed_time":2.909271641,"remaining_time":3.748100536},
{"learn":[0.353129647],"iteration":437,"passed_time":2.91601766,"remaining_time":3.741556906},
{"learn":[0.3529950191],"iteration":438,"passed_time":2.923090866,"remaining_time":3.735430469},
{"learn":[0.3529221288],"iteration":439,"passed_time":2.929796443,"remaining_time":3.728831837},
{"learn":[0.3527781987],"iteration":440,"passed_time":2.936467342,"remaining_time":3.722188763},
{"learn":[0.3525948796],"iteration":441,"passed_time":2.94326794,"remaining_time":3.7157093},
{"learn":[0.3524699531],"iteration":442,"passed_time":2.951892734,"remaining_time":3.711522015},
{"learn":[0.3524054111],"iteration":443,"passed_time":2.958671939,"remaining_time":3.7050036},
{"learn":[0.3522289573],"iteration":444,"passed_time":2.966317637,"remaining_time":3.699564694},
{"learn":[0.3521228955],"iteration":445,"passed_time":2.973434267,"remaining_time":3.693458708},
{"learn":[0.3519659594],"iteration":446,"passed_time":2.979231765,"remaining_time":3.685716255},
{"learn":[0.3518690387],"iteration":447,"passed_time":2.986287792,"remaining_time":3.679533172},
{"learn":[0.3517701971],"iteration":448,"passed_time":2.99238012,"remaining_time":3.672163577},
{"learn":[0.3517208035],"iteration":449,"passed_time":2.999992196,"remaining_time":3.666657129},
{"learn":[0.3515958978],"iteration":450,"passed_time":3.006347519,"remaining_time":3.659611503},
{"learn":[0.3514888976],"iteration":451,"passed_time":3.01259333,"remaining_time":3.652436162},
{"learn":[0.3513501351],"iteration":452,"passed_time":3.019731899,"remaining_time":3.646342933},
{"learn":[0.3512814822],"iteration":453,"passed_time":3.025833323,"remaining_time":3.638997785},
{"learn":[0.3511444716],"iteration":454,"passed_time":3.033472396,"remaining_time":3.633499903},
{"learn":[0.3510403601],"iteration":455,"passed_time":3.038899362,"remaining_time":3.625353625},
{"learn":[0.3508989921],"iteration":456,"passed_time":3.046072038,"remaining_time":3.619293472},
{"learn":[0.3508152073],"iteration":457,"passed_time":3.05228305,"remaining_time":3.612090421},
{"learn":[0.3506812981],"iteration":458,"passed_time":3.058850406,"remaining_time":3.605311699},
{"learn":[0.3505566518],"iteration":459,"passed_time":3.065908457,"remaining_time":3.599109928},
{"learn":[0.3504320993],"iteration":460,"passed_time":3.071365144,"remaining_time":3.591032131},
{"learn":[0.3503040029],"iteration":461,"passed_time":3.078560653,"remaining_time":3.584990544},
{"learn":[0.3501912889],"iteration":462,"passed_time":3.08457768,"remaining_time":3.577577136},
{"learn":[0.3500061601],"iteration":463,"passed_time":3.091471139,"remaining_time":3.571182178},
{"learn":[0.3498756783],"iteration":464,"passed_time":3.098033168,"remaining_time":3.564403752},
{"learn":[0.3497678473],"iteration":465,"passed_time":3.104540327,"remaining_time":3.557563379},
{"learn":[0.3495569579],"iteration":466,"passed_time":3.110489686,"remaining_time":3.5500878},
{"learn":[0.34947649],"iteration":467,"passed_time":3.116444083,"remaining_time":3.542624471},
{"learn":[0.3493550482],"iteration":468,"passed_time":3.122899313,"remaining_time":3.535734617},
{"learn":[0.3491897197],"iteration":469,"passed_time":3.129258212,"remaining_time":3.528737983},
{"learn":[0.3490843112],"iteration":470,"passed_time":3.136201078,"remaining_time":3.522399937},
{"learn":[0.3489872076],"iteration":471,"passed_time":3.143723221,"remaining_time":3.516707332},
{"learn":[0.3488866769],"iteration":472,"passed_time":3.150271287,"remaining_time":3.509921709},
{"learn":[0.3487941807],"iteration":473,"passed_time":3.15710824,"remaining_time":3.503457667},
{"learn":[0.3487007881],"iteration":474,"passed_time":3.162871167,"remaining_time":3.495804974},
{"learn":[0.3485681779],"iteration":475,"passed_time":3.168780668,"remaining_time":3.488321576},
{"learn":[0.3484110013],"iteration":476,"passed_time":3.175121353,"remaining_time":3.481317542},
{"learn":[0.3482907541],"iteration":477,"passed_time":3.18184145,"remaining_time":3.474730621},
{"learn":[0.3481574647],"iteration":478,"passed_time":3.188189944,"remaining_time":3.467738958},
{"learn":[0.3479821454],"iteration":479,"passed_time":3.194521098,"remaining_time":3.460731189},
{"learn":[0.347858495],"iteration":480,"passed_time":3.2002494,"remaining_time":3.453075756},
{"learn":[0.3477195573],"iteration":481,"passed_time":3.20703064,"remaining_time":3.446559899},
{"learn":[0.3475803499],"iteration":482,"passed_time":3.214869005,"remaining_time":3.441174483},
{"learn":[0.3474527713],"iteration":483,"passed_time":3.220814066,"remaining_time":3.433760451},
{"learn":[0.3472577761],"iteration":484,"passed_time":3.228109958,"remaining_time":3.427786863},
{"learn":[0.3471606928],"iteration":485,"passed_time":3.235027124,"remaining_time":3.421407288},
{"learn":[0.3470431082],"iteration":486,"passed_time":3.241463536,"remaining_time":3.414519085},
{"learn":[0.3469093826],"iteration":487,"passed_time":3.248921808,"remaining_time":3.408704848},
{"learn":[0.3467867844],"iteration":488,"passed_time":3.255684218,"remaining_time":3.402156719},
{"learn":[0.3466672378],"iteration":489,"passed_time":3.263153018,"remaining_time":3.396342937},
{"learn":[0.3465458331],"iteration":490,"passed_time":3.268801353,"remaining_time":3.388635211},
{"learn":[0.3464504539],"iteration":491,"passed_time":3.276009708,"remaining_time":3.382546609},
{"learn":[0.3463632222],"iteration":492,"passed_time":3.282319838,"remaining_time":3.375529732},
{"learn":[0.3462012461],"iteration":493,"passed_time":3.290328096,"remaining_time":3.370255095},
{"learn":[0.3461010063],"iteration":494,"passed_time":3.297129934,"remaining_time":3.36373862},
{"learn":[0.3459563222],"iteration":495,"passed_time":3.303598297,"remaining_time":3.35688214},
{"learn":[0.3458477985],"iteration":496,"passed_time":3.310513611,"remaining_time":3.35047957},
{"learn":[0.3457238673],"iteration":497,"passed_time":3.31749359,"remaining_time":3.344140124},
{"learn":[0.3455513845],"iteration":498,"passed_time":3.324056542,"remaining_time":3.337379414},
{"learn":[0.3454724742],"iteration":499,"passed_time":3.32984754,"remaining_time":3.32984754},
{"learn":[0.3452766794],"iteration":500,"passed_time":3.336958732,"remaining_time":3.32363754},
{"learn":[0.3451672829],"iteration":501,"passed_time":3.343295637,"remaining_time":3.316655831},
{"learn":[0.3450431254],"iteration":502,"passed_time":3.350794425,"remaining_time":3.31082471},
{"learn":[0.3449089309],"iteration":503,"passed_time":3.357654663,"remaining_time":3.304358557},
{"learn":[0.3448313289],"iteration":504,"passed_time":3.364340292,"remaining_time":3.297719692},
{"learn":[0.3447124331],"iteration":505,"passed_time":3.370355515,"remaining_time":3.290426135},
{"learn":[0.3445952745],"iteration":506,"passed_time":3.376168864,"remaining_time":3.282941321},
{"learn":[0.3444576273],"iteration":507,"passed_time":3.383316995,"remaining_time":3.27675583},
{"learn":[0.3443802299],"iteration":508,"passed_time":3.389060413,"remaining_time":3.269211518},
{"learn":[0.3442600025],"iteration":509,"passed_time":3.396741474,"remaining_time":3.263535926},
{"learn":[0.3441195483],"iteration":510,"passed_time":3.403424389,"remaining_time":3.256897311},
{"learn":[0.3439285709],"iteration":511,"passed_time":3.411452157,"remaining_time":3.251540337},
{"learn":[0.3437741131],"iteration":512,"passed_time":3.417965172,"remaining_time":3.244734969},
{"learn":[0.3436720858],"iteration":513,"passed_time":3.424462296,"remaining_time":3.237915711},
{"learn":[0.3434830417],"iteration":514,"passed_time":3.431045552,"remaining_time":3.231178821},
{"learn":[0.3433553253],"iteration":515,"passed_time":3.43799136,"remaining_time":3.224782594},
{"learn":[0.343249668],"iteration":516,"passed_time":3.444661919,"remaining_time":3.218127092},
{"learn":[0.3431474068],"iteration":517,"passed_time":3.450809618,"remaining_time":3.210985011},
{"learn":[0.3430738885],"iteration":518,"passed_time":3.460343731,"remaining_time":3.20698523},
{"learn":[0.3430109206],"iteration":519,"passed_time":3.46683633,"remaining_time":3.200156613},
{"learn":[0.3428514221],"iteration":520,"passed_time":3.474159067,"remaining_time":3.194092501},
{"learn":[0.3427931847],"iteration":521,"passed_time":3.480784071,"remaining_time":3.187384648},
{"learn":[0.3427001504],"iteration":522,"passed_time":3.487788913,"remaining_time":3.18102354},
{"learn":[0.3426225814],"iteration":523,"passed_time":3.494945439,"remaining_time":3.174797765},
{"learn":[0.342538932],"iteration":524,"passed_time":3.502272656,"remaining_time":3.168722879},
{"learn":[0.3424082451],"iteration":525,"passed_time":3.508605212,"remaining_time":3.161746902},
{"learn":[0.3422935581],"iteration":526,"passed_time":3.514715204,"remaining_time":3.154573608},
{"learn":[0.3421777598],"iteration":527,"passed_time":3.521346699,"remaining_time":3.147870534},
{"learn":[0.3421121104],"iteration":528,"passed_time":3.527079095,"remaining_time":3.14036721},
{"learn":[0.3420010153],"iteration":529,"passed_time":3.533775141,"remaining_time":3.133725125},
{"learn":[0.3419332602],"iteration":530,"passed_time":3.54017389,"remaining_time":3.126820253},
{"learn":[0.3417808788],"iteration":531,"passed_time":3.546998562,"remaining_time":3.120291968},
{"learn":[0.3416553521],"iteration":532,"passed_time":3.553587625,"remaining_time":3.113556137},
{"learn":[0.3415488203],"iteration":533,"passed_time":3.559382534,"remaining_time":3.106127829},
{"learn":[0.341439918],"iteration":534,"passed_time":3.56598733,"remaining_time":3.099409548},
{"learn":[0.3413302398],"iteration":535,"passed_time":3.571778568,"remaining_time":3.091987417},
{"learn":[0.3412570987],"iteration":536,"passed_time":3.578765248,"remaining_time":3.085602067},
{"learn":[0.3411037068],"iteration":537,"passed_time":3.585029175,"remaining_time":3.078593827},
{"learn":[0.3410498266],"iteration":538,"passed_time":3.591165865,"remaining_time":3.071479525},
{"learn":[0.3409844954],"iteration":539,"passed_time":3.597699963,"remaining_time":3.064707376},
{"learn":[0.3408751328],"iteration":540,"passed_time":3.603270425,"remaining_time":3.057118531},
{"learn":[0.3407478489],"iteration":541,"passed_time":3.609677569,"remaining_time":3.050244145},
{"learn":[0.3406210222],"iteration":542,"passed_time":3.615795274,"remaining_time":3.043127882},
{"learn":[0.3404992255],"iteration":543,"passed_time":3.622859853,"remaining_time":3.036808994},
{"learn":[0.3403487192],"iteration":544,"passed_time":3.630523915,"remaining_time":3.030987856},
{"learn":[0.3402294332],"iteration":545,"passed_time":3.637852616,"remaining_time":3.024881113},
{"learn":[0.3401072844],"iteration":546,"passed_time":3.644584817,"remaining_time":3.018275909},
{"learn":[0.3399699107],"iteration":547,"passed_time":3.651658064,"remaining_time":3.011951541},
{"learn":[0.3398761855],"iteration":548,"passed_time":3.658445637,"remaining_time":3.005389767},
{"learn":[0.339772728],"iteration":549,"passed_time":3.664390347,"remaining_time":2.998137557},
{"learn":[0.3396175864],"iteration":550,"passed_time":3.671433022,"remaining_time":2.991784803},
{"learn":[0.3395376503],"iteration":551,"passed_time":3.677949648,"remaining_time":2.985002613},
{"learn":[0.339448158],"iteration":552,"passed_time":3.685902046,"remaining_time":2.979381943},
{"learn":[0.3392934853],"iteration":553,"passed_time":3.692105523,"remaining_time":2.97234488},
{"learn":[0.3392265766],"iteration":554,"passed_time":3.698853096,"remaining_time":2.965747077},
{"learn":[0.339120449],"iteration":555,"passed_time":3.705102903,"remaining_time":2.958751239},
{"learn":[0.3390125286],"iteration":556,"passed_time":3.71074813,"remaining_time":2.951277238},
{"learn":[0.3389625693],"iteration":557,"passed_time":3.717266432,"remaining_time":2.944501367},
{"learn":[0.3388252713],"iteration":558,"passed_time":3.723348385,"remaining_time":2.937382179},
{"learn":[0.3386614066],"iteration":559,"passed_time":3.73121949,"remaining_time":2.931672457},
{"learn":[0.3385854411],"iteration":560,"passed_time":3.737182114,"remaining_time":2.924461583},
{"learn":[0.3384847135],"iteration":561,"passed_time":3.74303749,"remaining_time":2.917171567},
{"learn":[0.3382994865],"iteration":562,"passed_time":3.748762831,"remaining_time":2.909785714},
{"learn":[0.338247041],"iteration":563,"passed_time":3.756756219,"remaining_time":2.904159063},
{"learn":[0.3381566373],"iteration":564,"passed_time":3.765537171,"remaining_time":2.899130388},
{"learn":[0.3380519323],"iteration":565,"passed_time":3.771095864,"remaining_time":2.891617676},
{"learn":[0.3379545607],"iteration":566,"passed_time":3.778278371,"remaining_time":2.885351913},
{"learn":[0.3378774289],"iteration":567,"passed_time":3.784007724,"remaining_time":2.877977706},
{"learn":[0.3377420297],"iteration":568,"passed_time":3.790610004,"remaining_time":2.871270495},
{"learn":[0.3375713521],"iteration":569,"passed_time":3.797193668,"remaining_time":2.86454961},
{"learn":[0.3374352463],"iteration":570,"passed_time":3.803607958,"remaining_time":2.857701951},
{"learn":[0.3373571741],"iteration":571,"passed_time":3.810234292,"remaining_time":2.85101447},
{"learn":[0.3372500013],"iteration":572,"passed_time":3.816360637,"remaining_time":2.843954611},
{"learn":[0.3371916389],"iteration":573,"passed_time":3.823750828,"remaining_time":2.83783598},
{"learn":[0.3370623058],"iteration":574,"passed_time":3.829987021,"remaining_time":2.830859972},
{"learn":[0.336929211],"iteration":575,"passed_time":3.83757969,"remaining_time":2.82488505},
{"learn":[0.3368788937],"iteration":576,"passed_time":3.844096169,"remaining_time":2.818115562},
{"learn":[0.336725967],"iteration":577,"passed_time":3.851083758,"remaining_time":2.81169091},
{"learn":[0.3366693268],"iteration":578,"passed_time":3.856762265,"remaining_time":2.804312459},
{"learn":[0.3365475965],"iteration":579,"passed_time":3.862001553,"remaining_time":2.796621814},
{"learn":[0.3364760137],"iteration":580,"passed_time":3.869524967,"remaining_time":2.790586853},
{"learn":[0.3363721892],"iteration":581,"passed_time":3.875836388,"remaining_time":2.783676306},
{"learn":[0.336251732],"iteration":582,"passed_time":3.882790288,"remaining_time":2.777227359},
{"learn":[0.3361912794],"iteration":583,"passed_time":3.88905204,"remaining_time":2.770283645},
{"learn":[0.3360325418],"iteration":584,"passed_time":3.896074599,"remaining_time":2.763881981},
{"learn":[0.3358793827],"iteration":585,"passed_time":3.903062185,"remaining_time":2.757453489},
{"learn":[0.3357613471],"iteration":586,"passed_time":3.908679642,"remaining_time":2.750059101},
{"learn":[0.3356498622],"iteration":587,"passed_time":3.915260401,"remaining_time":2.743345723},
{"learn":[0.3355665936],"iteration":588,"passed_time":3.920891634,"remaining_time":2.735970224},
{"learn":[0.3354673011],"iteration":589,"passed_time":3.927960731,"remaining_time":2.72959983},
{"learn":[0.3353604616],"iteration":590,"passed_time":3.93438518,"remaining_time":2.722780945},
{"learn":[0.3352695038],"iteration":591,"passed_time":3.940300302,"remaining_time":2.71561237},
{"learn":[0.3351341933],"iteration":592,"passed_time":3.94645137,"remaining_time":2.708609962},
{"learn":[0.3350095374],"iteration":593,"passed_time":3.952194869,"remaining_time":2.701331847},
{"learn":[0.3348975071],"iteration":594,"passed_time":3.959265009,"remaining_time":2.694961897},
{"learn":[0.334796422],"iteration":595,"passed_time":3.966358469,"remaining_time":2.688605405},
{"learn":[0.3346686509],"iteration":596,"passed_time":3.974664026,"remaining_time":2.683064661},
{"learn":[0.3345998599],"iteration":597,"passed_time":3.980656861,"remaining_time":2.675959963},
{"learn":[0.33450483],"iteration":598,"passed_time":3.986579314,"remaining_time":2.668811861},
{"learn":[0.3344115532],"iteration":599,"passed_time":3.992515245,"remaining_time":2.66167683},
{"learn":[0.334302221],"iteration":600,"passed_time":3.999157099,"remaining_time":2.655014447},
{"learn":[0.3341996778],"iteration":601,"passed_time":4.005524638,"remaining_time":2.648170774},
{"learn":[0.334094235],"iteration":602,"passed_time":4.011693666,"remaining_time":2.641197986},
{"learn":[0.3339922864],"iteration":603,"passed_time":4.018633154,"remaining_time":2.634732995},
{"learn":[0.3338481234],"iteration":604,"passed_time":4.024802127,"remaining_time":2.627763372},
{"learn":[0.3337247948],"iteration":605,"passed_time":4.030279575,"remaining_time":2.620346786},
{"learn":[0.3336237081],"iteration":606,"passed_time":4.036561249,"remaining_time":2.613457283},
{"learn":[0.3334732403],"iteration":607,"passed_time":4.043442563,"remaining_time":2.606956389},
{"learn":[0.3333340541],"iteration":608,"passed_time":4.051152034,"remaining_time":2.600985953},
{"learn":[0.3332557547],"iteration":609,"passed_time":4.057347621,"remaining_time":2.594041922},
{"learn":[0.3332013589],"iteration":610,"passed_time":4.064429063,"remaining_time":2.58766433},
{"learn":[0.3330614482],"iteration":611,"passed_time":4.070937923,"remaining_time":2.580921428},
{"learn":[0.3330020921],"iteration":612,"passed_time":4.078117992,"remaining_time":2.574603039},
{"learn":[0.3329083495],"iteration":613,"passed_time":4.083717973,"remaining_time":2.567288498},
{"learn":[0.3327652451],"iteration":614,"passed_time":4.089412254,"remaining_time":2.560038566},
{"learn":[0.332647202],"iteration":615,"passed_time":4.09640269,"remaining_time":2.553601677},
{"learn":[0.3325502924],"iteration":616,"passed_time":4.102813047,"remaining_time":2.546802912},
{"learn":[0.3324500378],"iteration":617,"passed_time":4.111021769,"remaining_time":2.541117016},
{"learn":[0.3322833485],"iteration":618,"passed_time":4.118851005,"remaining_time":2.535189391},
{"learn":[0.3321835584],"iteration":619,"passed_time":4.12662768,"remaining_time":2.529223417},
{"learn":[0.3320236075],"iteration":620,"passed_time":4.133181572,"remaining_time":2.522505339},
{"learn":[0.3319105599],"iteration":621,"passed_time":4.1396046,"remaining_time":2.515708262},
{"learn":[0.3318186048],"iteration":622,"passed_time":4.147222649,"remaining_time":2.509635535},
{"learn":[0.3317561008],"iteration":623,"passed_time":4.153550709,"remaining_time":2.502780556},
{"learn":[0.3316224291],"iteration":624,"passed_time":4.160900314,"remaining_time":2.496540189},
{"learn":[0.3314914921],"iteration":625,"passed_time":4.167319028,"remaining_time":2.489740122},
{"learn":[0.3313421319],"iteration":626,"passed_time":4.1737251,"remaining_time":2.482933752},
{"learn":[0.3312162917],"iteration":627,"passed_time":4.180491853,"remaining_time":2.476342308},
{"learn":[0.3311602988],"iteration":628,"passed_time":4.18802542,"remaining_time":2.470202593},
{"learn":[0.3310143706],"iteration":629,"passed_time":4.194199802,"remaining_time":2.463260201},
{"learn":[0.3309545715],"iteration":630,"passed_time":4.201146921,"remaining_time":2.45677213},
{"learn":[0.3308840853],"iteration":631,"passed_time":4.207056542,"remaining_time":2.449678493},
{"learn":[0.3307870948],"iteration":632,"passed_time":4.21255301,"remaining_time":2.44234906},
{"learn":[0.3307202146],"iteration":633,"passed_time":4.218989994,"remaining_time":2.435568356},
{"learn":[0.3306102847],"iteration":634,"passed_time":4.225054276,"remaining_time":2.428574505},
{"learn":[0.3305038754],"iteration":635,"passed_time":4.231853166,"remaining_time":2.422004013},
{"learn":[0.330459031],"iteration":636,"passed_time":4.238379744,"remaining_time":2.415277625},
{"learn":[0.3303985498],"iteration":637,"passed_time":4.244107923,"remaining_time":2.408098853},
{"learn":[0.3302841039],"iteration":638,"passed_time":4.2510101,"remaining_time":2.401587865},
{"learn":[0.3301967372],"iteration":639,"passed_time":4.25653249,"remaining_time":2.394299526},
{"learn":[0.3301166816],"iteration":640,"passed_time":4.263686868,"remaining_time":2.387930711},
{"learn":[0.3300305729],"iteration":641,"passed_time":4.269595704,"remaining_time":2.380864894},
{"learn":[0.3299709193],"iteration":642,"passed_time":4.276142265,"remaining_time":2.374156747},
{"learn":[0.3298462959],"iteration":643,"passed_time":4.282674098,"remaining_time":2.367440961},
{"learn":[0.329777621],"iteration":644,"passed_time":4.289163061,"remaining_time":2.36070215},
{"learn":[0.3296663315],"iteration":645,"passed_time":4.296094591,"remaining_time":2.354206634},
{"learn":[0.3295442349],"iteration":646,"passed_time":4.30224363,"remaining_time":2.347282846},
{"learn":[0.329428481],"iteration":647,"passed_time":4.308945069,"remaining_time":2.340661519},
{"learn":[0.329352387],"iteration":648,"passed_time":4.316487052,"remaining_time":2.334494538},
{"learn":[0.3292279375],"iteration":649,"passed_time":4.3325562,"remaining_time":2.332914877},
{"learn":[0.3291415778],"iteration":650,"passed_time":4.340246549,"remaining_time":2.326798841},
{"learn":[0.3290819128],"iteration":651,"passed_time":4.348454859,"remaining_time":2.320954434},
{"learn":[0.3290013986],"iteration":652,"passed_time":4.357625746,"remaining_time":2.315614294},
{"learn":[0.3289000675],"iteration":653,"passed_time":4.364771301,"remaining_time":2.309190933},
{"learn":[0.3288399616],"iteration":654,"passed_time":4.372874387,"remaining_time":2.303269715},
{"learn":[0.3287192042],"iteration":655,"passed_time":4.380108765,"remaining_time":2.296886303},
{"learn":[0.3286267352],"iteration":656,"passed_time":4.386167652,"remaining_time":2.289886613},
{"learn":[0.3285032377],"iteration":657,"passed_time":4.392443004,"remaining_time":2.283002291},
{"learn":[0.3284382747],"iteration":658,"passed_time":4.400111282,"remaining_time":2.276840587},
{"learn":[0.3283620827],"iteration":659,"passed_time":4.406286329,"remaining_time":2.269905079},
{"learn":[0.3282426791],"iteration":660,"passed_time":4.412297008,"remaining_time":2.262887573},
{"learn":[0.3281438792],"iteration":661,"passed_time":4.418243529,"remaining_time":2.255840351},
{"learn":[0.3280874059],"iteration":662,"passed_time":4.423840664,"remaining_time":2.248618859},
{"learn":[0.3280032823],"iteration":663,"passed_time":4.431316553,"remaining_time":2.242352955},
{"learn":[0.3278817127],"iteration":664,"passed_time":4.438002398,"remaining_time":2.235685418},
{"learn":[0.3277904751],"iteration":665,"passed_time":4.444563171,"remaining_time":2.228955104},
{"learn":[0.3277077295],"iteration":666,"passed_time":4.450887494,"remaining_time":2.22210725},
{"learn":[0.3276003057],"iteration":667,"passed_time":4.456751574,"remaining_time":2.215032219},
{"learn":[0.327539992],"iteration":668,"passed_time":4.463601916,"remaining_time":2.208448781},
{"learn":[0.3274789534],"iteration":669,"passed_time":4.469282023,"remaining_time":2.201288161},
{"learn":[0.3273716426],"iteration":670,"passed_time":4.476516478,"remaining_time":2.19489407},
{"learn":[0.3272599128],"iteration":671,"passed_time":4.484549496,"remaining_time":2.188887254},
{"learn":[0.3271892812],"iteration":672,"passed_time":4.492092322,"remaining_time":2.18263624},
{"learn":[0.327100063],"iteration":673,"passed_time":4.498367736,"remaining_time":2.175768371},
{"learn":[0.3270433906],"iteration":674,"passed_time":4.50615687,"remaining_time":2.169631085},
{"learn":[0.3269734333],"iteration":675,"passed_time":4.512958083,"remaining_time":2.163015412},
{"learn":[0.3268815351],"iteration":676,"passed_time":4.518945105,"remaining_time":2.156010737},
{"learn":[0.3267742706],"iteration":677,"passed_time":4.525842942,"remaining_time":2.149441633},
{"learn":[0.3266412668],"iteration":678,"passed_time":4.531232845,"remaining_time":2.142158679},
{"learn":[0.3265532487],"iteration":679,"passed_time":4.53843372,"remaining_time":2.135733515},
{"learn":[0.3264382221],"iteration":680,"passed_time":4.544478404,"remaining_time":2.12876448},
{"learn":[0.3263658684],"iteration":681,"passed_time":4.551410772,"remaining_time":2.122212061},
{"learn":[0.3262294579],"iteration":682,"passed_time":4.557548464,"remaining_time":2.115289697},
{"learn":[0.3260981906],"iteration":683,"passed_time":4.563432231,"remaining_time":2.108252317},
{"learn":[0.3260089219],"iteration":684,"passed_time":4.571909928,"remaining_time":2.102411135},
{"learn":[0.3259123195],"iteration":685,"passed_time":4.578577602,"remaining_time":2.095733771},
{"learn":[0.3258426156],"iteration":686,"passed_time":4.584735826,"remaining_time":2.088824328},
{"learn":[0.3257236851],"iteration":687,"passed_time":4.591137928,"remaining_time":2.082027665},
{"learn":[0.3256431777],"iteration":688,"passed_time":4.599889535,"remaining_time":2.076292664},
{"learn":[0.3255944686],"iteration":689,"passed_time":4.605596849,"remaining_time":2.069181193},
{"learn":[0.3254475995],"iteration":690,"passed_time":4.613409285,"remaining_time":2.063015151},
{"learn":[0.325339671],"iteration":691,"passed_time":4.619587159,"remaining_time":2.056116828},
{"learn":[0.3252567926],"iteration":692,"passed_time":4.626269552,"remaining_time":2.049444087},
{"learn":[0.3251955418],"iteration":693,"passed_time":4.632785336,"remaining_time":2.042697857},
{"learn":[0.3251488168],"iteration":694,"passed_time":4.638987946,"remaining_time":2.035814854},
{"learn":[0.3251032228],"iteration":695,"passed_time":4.644827524,"remaining_time":2.028775241},
{"learn":[0.3249639685],"iteration":696,"passed_time":4.650959126,"remaining_time":2.021866019},
{"learn":[0.3248468173],"iteration":697,"passed_time":4.659109087,"remaining_time":2.015832298},
{"learn":[0.3246894133],"iteration":698,"passed_time":4.666115233,"remaining_time":2.009299979},
{"learn":[0.3245880908],"iteration":699,"passed_time":4.673282618,"remaining_time":2.002835408},
{"learn":[0.3245304268],"iteration":700,"passed_time":4.67902537,"remaining_time":1.995761178},
{"learn":[0.324473918],"iteration":701,"passed_time":4.686767597,"remaining_time":1.989539521},
{"learn":[0.324387814],"iteration":702,"passed_time":4.693976946,"remaining_time":1.983088411},
{"learn":[0.3243004652],"iteration":703,"passed_time":4.700107856,"remaining_time":1.976181712},
{"learn":[0.3242218751],"iteration":704,"passed_time":4.70622863,"remaining_time":1.969272973},
{"learn":[0.3241253313],"iteration":705,"passed_time":4.712101705,"remaining_time":1.962263316},
{"learn":[0.3240390627],"iteration":706,"passed_time":4.719391832,"remaining_time":1.95584414},
{"learn":[0.323932634],"iteration":707,"passed_time":4.725672377,"remaining_time":1.949006122},
{"learn":[0.3238356337],"iteration":708,"passed_time":4.732618722,"remaining_time":1.942442945},
{"learn":[0.323764469],"iteration":709,"passed_time":4.73861868,"remaining_time":1.935492137},
{"learn":[0.3236522534],"iteration":710,"passed_time":4.744249557,"remaining_time":1.928393983},
{"learn":[0.3235690261],"iteration":711,"passed_time":4.750940459,"remaining_time":1.921728725},
{"learn":[0.3234685089],"iteration":712,"passed_time":4.756971136,"remaining_time":1.914797638},
{"learn":[0.323374921],"iteration":713,"passed_time":4.76402318,"remaining_time":1.908278193},
{"learn":[0.3232801163],"iteration":714,"passed_time":4.77037053,"remaining_time":1.901476365},
{"learn":[0.323144322],"iteration":715,"passed_time":4.77702012,"remaining_time":1.89479569},
{"learn":[0.3230716875],"iteration":716,"passed_time":4.783850265,"remaining_time":1.888186367},
{"learn":[0.3229977256],"iteration":717,"passed_time":4.78915279,"remaining_time":1.880976444},
{"learn":[0.3229020749],"iteration":718,"passed_time":4.795381586,"remaining_time":1.874133833},
{"learn":[0.3228159846],"iteration":719,"passed_time":4.801585224,"remaining_time":1.867283143},
{"learn":[0.3227445378],"iteration":720,"passed_time":4.808743771,"remaining_time":1.860803761},
{"learn":[0.3226947292],"iteration":721,"passed_time":4.814772831,"remaining_time":1.8538876},
{"learn":[0.322572754],"iteration":722,"passed_time":4.82065398,"remaining_time":1.846917223},
{"learn":[0.3224483244],"iteration":723,"passed_time":4.828719256,"remaining_time":1.840782479},
{"learn":[0.3223943758],"iteration":724,"passed_time":4.834541143,"remaining_time":1.833791468},
{"learn":[0.3223338038],"iteration":725,"passed_time":4.842768417,"remaining_time":1.827711496},
{"learn":[0.3221711923],"iteration":726,"passed_time":4.849164823,"remaining_time":1.820938097},
{"learn":[0.3220792042],"iteration":727,"passed_time":4.857075962,"remaining_time":1.814731678},
{"learn":[0.3219667577],"iteration":728,"passed_time":4.863000369,"remaining_time":1.80778203},
{"learn":[0.3218931861],"iteration":729,"passed_time":4.870085326,"remaining_time":1.801264435},
{"learn":[0.3217578524],"iteration":730,"passed_time":4.875736763,"remaining_time":1.794217769},
{"learn":[0.3216942044],"iteration":731,"passed_time":4.881825658,"remaining_time":1.787335077},
{"learn":[0.3216347431],"iteration":732,"passed_time":4.888143351,"remaining_time":1.780537892},
{"learn":[0.3215810724],"iteration":733,"passed_time":4.893617618,"remaining_time":1.773436357},
{"learn":[0.321512603],"iteration":734,"passed_time":4.900501189,"remaining_time":1.766847367},
{"learn":[0.3214292111],"iteration":735,"passed_time":4.906638488,"remaining_time":1.759989893},
{"learn":[0.3213778108],"iteration":736,"passed_time":4.913062381,"remaining_time":1.753236643},
{"learn":[0.3213425277],"iteration":737,"passed_time":4.91857003,"remaining_time":1.746159008},
{"learn":[0.3212556645],"iteration":738,"passed_time":4.924299895,"remaining_time":1.739164103},
{"learn":[0.321165412],"iteration":739,"passed_time":4.931652565,"remaining_time":1.732742793},
{"learn":[0.3211084839],"iteration":740,"passed_time":4.93816965,"remaining_time":1.726026909},
{"learn":[0.3209791856],"iteration":741,"passed_time":4.944787689,"remaining_time":1.719346663},
{"learn":[0.3208981421],"iteration":742,"passed_time":4.951418277,"remaining_time":1.712670925},
{"learn":[0.3207970663],"iteration":743,"passed_time":4.9571961,"remaining_time":1.705701884},
{"learn":[0.3206744832],"iteration":744,"passed_time":4.964304518,"remaining_time":1.699191479},
{"learn":[0.3206158861],"iteration":745,"passed_time":4.970384439,"remaining_time":1.692329286},
{"learn":[0.3204665778],"iteration":746,"passed_time":4.9777852,"remaining_time":1.68591654},
{"learn":[0.3203692491],"iteration":747,"passed_time":4.984267487,"remaining_time":1.67919172},
{"learn":[0.3202642572],"iteration":748,"passed_time":4.991960255,"remaining_time":1.672873196},
{"learn":[0.3201427408],"iteration":749,"passed_time":5.000455563,"remaining_time":1.666818521},
{"learn":[0.3200342815],"iteration":750,"passed_time":5.007838508,"remaining_time":1.660388533},
{"learn":[0.3199753082],"iteration":751,"passed_time":5.0153807,"remaining_time":1.654008529},
{"learn":[0.3198862304],"iteration":752,"passed_time":5.023738341,"remaining_time":1.647892922},
{"learn":[0.3197575452],"iteration":753,"passed_time":5.030177402,"remaining_time":1.641145412},
{"learn":[0.3196796679],"iteration":754,"passed_time":5.037716009,"remaining_time":1.634755526},
{"learn":[0.3195421423],"iteration":755,"passed_time":5.043957299,"remaining_time":1.62794389},
{"learn":[0.3194144745],"iteration":756,"passed_time":5.050625668,"remaining_time":1.621270855},
{"learn":[0.3193382981],"iteration":757,"passed_time":5.058127761,"remaining_time":1.614864008},
{"learn":[0.3192070787],"iteration":758,"passed_time":5.064092949,"remaining_time":1.607966272},
{"learn":[0.3190689967],"iteration":759,"passed_time":5.070567645,"remaining_time":1.601231888},
{"learn":[0.3189640932],"iteration":760,"passed_time":5.076086098,"remaining_time":1.594197868},
{"learn":[0.3188677224],"iteration":761,"passed_time":5.083389764,"remaining_time":1.587725412},
{"learn":[0.3187861346],"iteration":762,"passed_time":5.089589018,"remaining_time":1.580907729},
{"learn":[0.3187353974],"iteration":763,"passed_time":5.094937305,"remaining_time":1.573828801},
{"learn":[0.3186673465],"iteration":764,"passed_time":5.102108147,"remaining_time":1.567314268},
{"learn":[0.3185893123],"iteration":765,"passed_time":5.108223481,"remaining_time":1.56047558},
{"learn":[0.3184386932],"iteration":766,"passed_time":5.114727853,"remaining_time":1.553756962},
{"learn":[0.3183640822],"iteration":767,"passed_time":5.120324448,"remaining_time":1.546764677},
{"learn":[0.318284203],"iteration":768,"passed_time":5.125963958,"remaining_time":1.539788913},
{"learn":[0.3182069821],"iteration":769,"passed_time":5.132877789,"remaining_time":1.533197262},
{"learn":[0.3180669352],"iteration":770,"passed_time":5.140344791,"remaining_time":1.526769075},
{"learn":[0.3179779919],"iteration":771,"passed_time":5.148138775,"remaining_time":1.520434768},
{"learn":[0.317894176],"iteration":772,"passed_time":5.155403147,"remaining_time":1.513941157},
{"learn":[0.317774078],"iteration":773,"passed_time":5.16387727,"remaining_time":1.507798789},
{"learn":[0.3176526384],"iteration":774,"passed_time":5.170437988,"remaining_time":1.5010949},
{"learn":[0.3175519799],"iteration":775,"passed_time":5.178607237,"remaining_time":1.494855697},
{"learn":[0.3174080939],"iteration":776,"passed_time":5.185273004,"remaining_time":1.488180025},
{"learn":[0.317290927],"iteration":777,"passed_time":5.192070878,"remaining_time":1.481542076},
{"learn":[0.3171628851],"iteration":778,"passed_time":5.199165282,"remaining_time":1.47498784},
{"learn":[0.3171208471],"iteration":779,"passed_time":5.205451476,"remaining_time":1.468204262},
{"learn":[0.3170623211],"iteration":780,"passed_time":5.212826565,"remaining_time":1.461727295},
{"learn":[0.3169726144],"iteration":781,"passed_time":5.219318239,"remaining_time":1.45500176},
{"learn":[0.3168780915],"iteration":782,"passed_time":5.225746975,"remaining_time":1.448259379},
{"learn":[0.3168137231],"iteration":783,"passed_time":5.232930629,"remaining_time":1.441725786},
{"learn":[0.3167414794],"iteration":784,"passed_time":5.23944966,"remaining_time":1.435008506},
{"learn":[0.3166523731],"iteration":785,"passed_time":5.246732107,"remaining_time":1.428499581},
{"learn":[0.3166199385],"iteration":786,"passed_time":5.254313699,"remaining_time":1.422069654},
{"learn":[0.3165066425],"iteration":787,"passed_time":5.261488081,"remaining_time":1.41552725},
{"learn":[0.3164122073],"iteration":788,"passed_time":5.268212664,"remaining_time":1.408862956},
{"learn":[0.3163622532],"iteration":789,"passed_time":5.275003398,"remaining_time":1.402216093},
{"learn":[0.3162230958],"iteration":790,"passed_time":5.282137919,"remaining_time":1.395659703},
{"learn":[0.3161337837],"iteration":791,"passed_time":5.289946972,"remaining_time":1.389279003},
{"learn":[0.3160563309],"iteration":792,"passed_time":5.296901532,"remaining_time":1.382671648},
{"learn":[0.31602231],"iteration":793,"passed_time":5.303753173,"remaining_time":1.376036717},
{"learn":[0.3158826351],"iteration":794,"passed_time":5.309912364,"remaining_time":1.369222685},
{"learn":[0.315778922],"iteration":795,"passed_time":5.318619131,"remaining_time":1.363063194},
{"learn":[0.3156810077],"iteration":796,"passed_time":5.324973287,"remaining_time":1.356298089},
{"learn":[0.3156375187],"iteration":797,"passed_time":5.333984766,"remaining_time":1.35020667},
{"learn":[0.3155429495],"iteration":798,"passed_time":5.340174926,"remaining_time":1.343398198},
{"learn":[0.315470061],"iteration":799,"passed_time":5.348575482,"remaining_time":1.337143871},
{"learn":[0.3153851703],"iteration":800,"passed_time":5.355023877,"remaining_time":1.33039919},
{"learn":[0.3153096947],"iteration":801,"passed_time":5.362252449,"remaining_time":1.323847861},
{"learn":[0.3151796103],"iteration":802,"passed_time":5.368729762,"remaining_time":1.317110539},
{"learn":[0.3151021079],"iteration":803,"passed_time":5.375482615,"remaining_time":1.310441035},
{"learn":[0.3150110987],"iteration":804,"passed_time":5.381953988,"remaining_time":1.30370314},
{"learn":[0.3149489465],"iteration":805,"passed_time":5.387650657,"remaining_time":1.296779438},
{"learn":[0.3148945417],"iteration":806,"passed_time":5.395164571,"remaining_time":1.290293386},
{"learn":[0.3148450999],"iteration":807,"passed_time":5.400922928,"remaining_time":1.283387626},
{"learn":[0.314769849],"iteration":808,"passed_time":5.40844172,"remaining_time":1.276900332},
{"learn":[0.314637203],"iteration":809,"passed_time":5.414285415,"remaining_time":1.270017567},
{"learn":[0.3145680599],"iteration":810,"passed_time":5.421306759,"remaining_time":1.263411809},
{"learn":[0.3144314538],"iteration":811,"passed_time":5.427757415,"remaining_time":1.256672899},
{"learn":[0.3143401959],"iteration":812,"passed_time":5.432952531,"remaining_time":1.249645908},
{"learn":[0.3142593412],"iteration":813,"passed_time":5.439892185,"remaining_time":1.243022047},
{"learn":[0.3141380275],"iteration":814,"passed_time":5.445476258,"remaining_time":1.236089703},
{"learn":[0.3140351086],"iteration":815,"passed_time":5.452707703,"remaining_time":1.229532129},
{"learn":[0.3139290892],"iteration":816,"passed_time":5.458926323,"remaining_time":1.222746043},
{"learn":[0.313853313],"iteration":817,"passed_time":5.464507329,"remaining_time":1.215819479},
{"learn":[0.3137555835],"iteration":818,"passed_time":5.470288557,"remaining_time":1.20894045},
{"learn":[0.3136486214],"iteration":819,"passed_time":5.476490744,"remaining_time":1.202156505},
{"learn":[0.3135624469],"iteration":820,"passed_time":5.486041524,"remaining_time":1.196104059},
{"learn":[0.313489154],"iteration":821,"passed_time":5.49314105,"remaining_time":1.189512296},
{"learn":[0.3134328877],"iteration":822,"passed_time":5.501042688,"remaining_time":1.183091805},
{"learn":[0.3133353393],"iteration":823,"passed_time":5.508019772,"remaining_time":1.176470243},
{"learn":[0.3132738716],"iteration":824,"passed_time":5.526141174,"remaining_time":1.172211764},
{"learn":[0.3132052888],"iteration":825,"passed_time":5.536362545,"remaining_time":1.166255548},
{"learn":[0.313095753],"iteration":826,"passed_time":5.544109627,"remaining_time":1.159771421},
{"learn":[0.3129704413],"iteration":827,"passed_time":5.551929271,"remaining_time":1.153299317},
{"learn":[0.3128869557],"iteration":828,"passed_time":5.559504189,"remaining_time":1.146773482},
{"learn":[0.3128035198],"iteration":829,"passed_time":5.566590628,"remaining_time":1.140145068},
{"learn":[0.3127026066],"iteration":830,"passed_time":5.573700397,"remaining_time":1.133520297},
{"learn":[0.3126104424],"iteration":831,"passed_time":5.579724925,"remaining_time":1.126675225},
{"learn":[0.3124732271],"iteration":832,"passed_time":5.586087006,"remaining_time":1.119899796},
{"learn":[0.3123562197],"iteration":833,"passed_time":5.592500567,"remaining_time":1.113135605},
{"learn":[0.3122653616],"iteration":834,"passed_time":5.598199891,"remaining_time":1.106231116},
{"learn":[0.3121268511],"iteration":835,"passed_time":5.605197867,"remaining_time":1.09958427},
{"learn":[0.3120491919],"iteration":836,"passed_time":5.61274298,"remaining_time":1.093043137},
{"learn":[0.3119761502],"iteration":837,"passed_time":5.620577204,"remaining_time":1.086555498},
{"learn":[0.3119114049],"iteration":838,"passed_time":5.626994464,"remaining_time":1.07979274},
{"learn":[0.311842744],"iteration":839,"passed_time":5.633858115,"remaining_time":1.073115831},
{"learn":[0.3117267562],"iteration":840,"passed_time":5.640732424,"remaining_time":1.066440494},
{"learn":[0.3116234742],"iteration":841,"passed_time":5.646984757,"remaining_time":1.059647971},
{"learn":[0.3115494501],"iteration":842,"passed_time":5.653644341,"remaining_time":1.052932576},
{"learn":[0.3114971507],"iteration":843,"passed_time":5.660911246,"remaining_time":1.046329567},
{"learn":[0.3114007026],"iteration":844,"passed_time":5.667945669,"remaining_time":1.039682342},
{"learn":[0.3113495385],"iteration":845,"passed_time":5.675056567,"remaining_time":1.033048122},
{"learn":[0.3113115862],"iteration":846,"passed_time":5.683145653,"remaining_time":1.026589474},
{"learn":[0.3112087318],"iteration":847,"passed_time":5.690115935,"remaining_time":1.019926441},
{"learn":[0.3111079371],"iteration":848,"passed_time":5.698564001,"remaining_time":1.013525517},
{"learn":[0.3110168369],"iteration":849,"passed_time":5.704269701,"remaining_time":1.00663583},
{"learn":[0.3109713503],"iteration":850,"passed_time":5.712422015,"remaining_time":1.000177298},
{"learn":[0.3108648466],"iteration":851,"passed_time":5.719163939,"remaining_time":0.9934697923},
{"learn":[0.3107773445],"iteration":852,"passed_time":5.726750367,"remaining_time":0.9869077421},
{"learn":[0.3106750413],"iteration":853,"passed_time":5.734458117,"remaining_time":0.9803640341},
{"learn":[0.3105905463],"iteration":854,"passed_time":5.741569678,"remaining_time":0.9737164951},
{"learn":[0.310505547],"iteration":855,"passed_time":5.747903157,"remaining_time":0.9669369796},
{"learn":[0.310428514],"iteration":856,"passed_time":5.753599914,"remaining_time":0.9600522611},
{"learn":[0.3103966491],"iteration":857,"passed_time":5.759427222,"remaining_time":0.9531919178},
{"learn":[0.3103330569],"iteration":858,"passed_time":5.765655982,"remaining_time":0.946399876},
{"learn":[0.3102401375],"iteration":859,"passed_time":5.77298383,"remaining_time":0.9397880654},
{"learn":[0.3101452095],"iteration":860,"passed_time":5.779036496,"remaining_time":0.9329687258},
{"learn":[0.3100514338],"iteration":861,"passed_time":5.784920333,"remaining_time":0.9261241368},
{"learn":[0.3099461623],"iteration":862,"passed_time":5.791121462,"remaining_time":0.9193321441},
{"learn":[0.3098784694],"iteration":863,"passed_time":5.796703422,"remaining_time":0.9124440572},
{"learn":[0.3097437477],"iteration":864,"passed_time":5.803944509,"remaining_time":0.9058179291},
{"learn":[0.309692536],"iteration":865,"passed_time":5.809753196,"remaining_time":0.8989687394},
{"learn":[0.3095783259],"iteration":866,"passed_time":5.816654919,"remaining_time":0.8922896243},
{"learn":[0.3094698648],"iteration":867,"passed_time":5.82317406,"remaining_time":0.8855518156},
{"learn":[0.3093992421],"iteration":868,"passed_time":5.830351865,"remaining_time":0.8789138024},
{"learn":[0.3093577183],"iteration":869,"passed_time":5.836905306,"remaining_time":0.8721812526},
{"learn":[0.3093007929],"iteration":870,"passed_time":5.842874309,"remaining_time":0.8653625555},
{"learn":[0.3091938971],"iteration":871,"passed_time":5.850826034,"remaining_time":0.858836849},
{"learn":[0.3091453124],"iteration":872,"passed_time":5.857036175,"remaining_time":0.8520545181},
{"learn":[0.3090542719],"iteration":873,"passed_time":5.864754466,"remaining_time":0.8454909185},
{"learn":[0.3089732438],"iteration":874,"passed_time":5.870560193,"remaining_time":0.8386514562},
{"learn":[0.3088818382],"iteration":875,"passed_time":5.877002981,"remaining_time":0.8319045316},
{"learn":[0.3088077702],"iteration":876,"passed_time":5.883063851,"remaining_time":0.8251047363},
{"learn":[0.308698585],"iteration":877,"passed_time":5.888892279,"remaining_time":0.8182743257},
{"learn":[0.3086206026],"iteration":878,"passed_time":5.895822569,"remaining_time":0.8115978735},
{"learn":[0.3085651475],"iteration":879,"passed_time":5.902099614,"remaining_time":0.8048317656},
{"learn":[0.3084623719],"iteration":880,"passed_time":5.910687148,"remaining_time":0.7983788543},
{"learn":[0.3084262762],"iteration":881,"passed_time":5.916665911,"remaining_time":0.7915720833},
{"learn":[0.308355888],"iteration":882,"passed_time":5.924330753,"remaining_time":0.7849905981},
{"learn":[0.3082926925],"iteration":883,"passed_time":5.930982113,"remaining_time":0.778273671},
{"learn":[0.3082156144],"iteration":884,"passed_time":5.937788756,"remaining_time":0.77157707},
{"learn":[0.3081321951],"iteration":885,"passed_time":5.94392599,"remaining_time":0.7647940889},
{"learn":[0.3080420707],"iteration":886,"passed_time":5.950562441,"remaining_time":0.7580761622},
{"learn":[0.3078997519],"iteration":887,"passed_time":5.957617479,"remaining_time":0.7514112136},
{"learn":[0.3078053397],"iteration":888,"passed_time":5.963461784,"remaining_time":0.744594216},
{"learn":[0.3077417328],"iteration":889,"passed_time":5.969751611,"remaining_time":0.7378344687},
{"learn":[0.3076853045],"iteration":890,"passed_time":5.976206554,"remaining_time":0.7310959758},
{"learn":[0.307643135],"iteration":891,"passed_time":5.983494631,"remaining_time":0.7244589912},
{"learn":[0.3075414001],"iteration":892,"passed_time":5.990914082,"remaining_time":0.7178362897},
{"learn":[0.3074888353],"iteration":893,"passed_time":5.99953315,"remaining_time":0.7113540424},
{"learn":[0.3074024499],"iteration":894,"passed_time":6.005611468,"remaining_time":0.7045689432},
{"learn":[0.3073203905],"iteration":895,"passed_time":6.012389974,"remaining_time":0.6978666935},
{"learn":[0.307219403],"iteration":896,"passed_time":6.019673449,"remaining_time":0.6912222578},
{"learn":[0.3071132773],"iteration":897,"passed_time":6.026787569,"remaining_time":0.6845571626},
{"learn":[0.307067171],"iteration":898,"passed_time":6.033748228,"remaining_time":0.6778738277},
{"learn":[0.3069705131],"iteration":899,"passed_time":6.039590065,"remaining_time":0.6710655628},
{"learn":[0.306935679],"iteration":900,"passed_time":6.062457251,"remaining_time":0.666130153},
{"learn":[0.3068299771],"iteration":901,"passed_time":6.06842055,"remaining_time":0.6593184189},
{"learn":[0.3067079101],"iteration":902,"passed_time":6.07462192,"remaining_time":0.6525341376},
{"learn":[0.306626939],"iteration":903,"passed_time":6.081062014,"remaining_time":0.645776497},
{"learn":[0.3065931694],"iteration":904,"passed_time":6.086987097,"remaining_time":0.6389654963},
{"learn":[0.3065479282],"iteration":905,"passed_time":6.09377811,"remaining_time":0.632246294},
{"learn":[0.3064689933],"iteration":906,"passed_time":6.099839871,"remaining_time":0.6254521588},
{"learn":[0.3063515056],"iteration":907,"passed_time":6.107392484,"remaining_time":0.6188106922},
{"learn":[0.3062699733],"iteration":908,"passed_time":6.11349638,"remaining_time":0.6120221898},
{"learn":[0.3061890596],"iteration":909,"passed_time":6.119837063,"remaining_time":0.6052586106},
{"learn":[0.3061292766],"iteration":910,"passed_time":6.126658864,"remaining_time":0.5985429626},
{"learn":[0.3060282788],"iteration":911,"passed_time":6.133012131,"remaining_time":0.5917818722},
{"learn":[0.3059048778],"iteration":912,"passed_time":6.140281312,"remaining_time":0.585108953},
{"learn":[0.3058483756],"iteration":913,"passed_time":6.146117646,"remaining_time":0.5782999098},
{"learn":[0.3057579991],"iteration":914,"passed_time":6.154440491,"remaining_time":0.57172398},
{"learn":[0.3056648779],"iteration":915,"passed_time":6.160339384,"remaining_time":0.5649219523},
{"learn":[0.3055693043],"iteration":916,"passed_time":6.167628976,"remaining_time":0.5582477699},
{"learn":[0.3054629095],"iteration":917,"passed_time":6.176092404,"remaining_time":0.5516770993},
{"learn":[0.3053453155],"iteration":918,"passed_time":6.183986778,"remaining_time":0.5450521535},
{"learn":[0.3052675464],"iteration":919,"passed_time":6.191410036,"remaining_time":0.5383834814},
{"learn":[0.3051859358],"iteration":920,"passed_time":6.199412677,"remaining_time":0.5317628681},
{"learn":[0.3050644766],"iteration":921,"passed_time":6.20627163,"remaining_time":0.5250425023},
{"learn":[0.3049797673],"iteration":922,"passed_time":6.214746297,"remaining_time":0.518456625},
{"learn":[0.3048916793],"iteration":923,"passed_time":6.221409526,"remaining_time":0.5117176667},
{"learn":[0.3048266062],"iteration":924,"passed_time":6.229174662,"remaining_time":0.5050682158},
{"learn":[0.3047519397],"iteration":925,"passed_time":6.236070742,"remaining_time":0.4983469059},
{"learn":[0.3046641451],"iteration":926,"passed_time":6.242671946,"remaining_time":0.4916019979},
{"learn":[0.3045925485],"iteration":927,"passed_time":6.249026574,"remaining_time":0.4848382686},
{"learn":[0.3045135049],"iteration":928,"passed_time":6.254593874,"remaining_time":0.4780152476},
{"learn":[0.3044282654],"iteration":929,"passed_time":6.261665633,"remaining_time":0.471308166},
{"learn":[0.3043086604],"iteration":930,"passed_time":6.26768419,"remaining_time":0.4645222439},
{"learn":[0.3042265831],"iteration":931,"passed_time":6.27482186,"remaining_time":0.4578196207},
{"learn":[0.3041980449],"iteration":932,"passed_time":6.282028556,"remaining_time":0.4511210217},
{"learn":[0.3041286169],"iteration":933,"passed_time":6.288724455,"remaining_time":0.4443852398},
{"learn":[0.304041579],"iteration":934,"passed_time":6.29478595,"remaining_time":0.4376054404},
{"learn":[0.3039981704],"iteration":935,"passed_time":6.300730827,"remaining_time":0.4308192019},
{"learn":[0.3038902214],"iteration":936,"passed_time":6.308345294,"remaining_time":0.4241470155},
{"learn":[0.3037804585],"iteration":937,"passed_time":6.314401776,"remaining_time":0.4173698402},
{"learn":[0.3036667343],"iteration":938,"passed_time":6.32207897,"remaining_time":0.4106994858},
{"learn":[0.3035733893],"iteration":939,"passed_time":6.330564958,"remaining_time":0.4040786144},
{"learn":[0.3035042616],"iteration":940,"passed_time":6.337528932,"remaining_time":0.3973583496},
{"learn":[0.3034188081],"iteration":941,"passed_time":6.346861942,"remaining_time":0.3907834316},
{"learn":[0.303355863],"iteration":942,"passed_time":6.354179088,"remaining_time":0.3840808145},
{"learn":[0.3032432848],"iteration":943,"passed_time":6.361376283,"remaining_time":0.3773697795},
{"learn":[0.3031884473],"iteration":944,"passed_time":6.36755344,"remaining_time":0.3705983484},
{"learn":[0.3031386381],"iteration":945,"passed_time":6.37340097,"remaining_time":0.3638093577},
{"learn":[0.3030842931],"iteration":946,"passed_time":6.381520839,"remaining_time":0.3571495295},
{"learn":[0.3029590528],"iteration":947,"passed_time":6.387527391,"remaining_time":0.3503707008},
{"learn":[0.3028566054],"iteration":948,"passed_time":6.394744776,"remaining_time":0.3436585707},
{"learn":[0.3027574299],"iteration":949,"passed_time":6.400696805,"remaining_time":0.3368787792},
{"learn":[0.3026661224],"iteration":950,"passed_time":6.407021732,"remaining_time":0.3301199421},
{"learn":[0.302573839],"iteration":951,"passed_time":6.412887569,"remaining_time":0.323338869},
{"learn":[0.3025185129],"iteration":952,"passed_time":6.419364727,"remaining_time":0.3165898658},
{"learn":[0.3024631329],"iteration":953,"passed_time":6.42581536,"remaining_time":0.3098401536},
{"learn":[0.3023437236],"iteration":954,"passed_time":6.431364718,"remaining_time":0.3030485993},
{"learn":[0.3022754223],"iteration":955,"passed_time":6.438841062,"remaining_time":0.2963483334},
{"learn":[0.3022094217],"iteration":956,"passed_time":6.44521767,"remaining_time":0.2895970322},
{"learn":[0.3021474504],"iteration":957,"passed_time":6.45209,"remaining_time":0.2828682463},
{"learn":[0.3020575661],"iteration":958,"passed_time":6.458318148,"remaining_time":0.2761116205},
{"learn":[0.3019910567],"iteration":959,"passed_time":6.463998148,"remaining_time":0.2693332562},
{"learn":[0.3018754538],"iteration":960,"passed_time":6.470638109,"remaining_time":0.2625961355},
{"learn":[0.3017891085],"iteration":961,"passed_time":6.476822373,"remaining_time":0.2558412164},
{"learn":[0.3017182454],"iteration":962,"passed_time":6.484192554,"remaining_time":0.2491330472},
{"learn":[0.3016181837],"iteration":963,"passed_time":6.490271896,"remaining_time":0.242375299},
{"learn":[0.3015766445],"iteration":964,"passed_time":6.496521276,"remaining_time":0.235625124},
{"learn":[0.3014805816],"iteration":965,"passed_time":6.502984181,"remaining_time":0.2288835012},
{"learn":[0.3013184925],"iteration":966,"passed_time":6.509381662,"remaining_time":0.2221402222},
{"learn":[0.3012005333],"iteration":967,"passed_time":6.51611406,"remaining_time":0.2154087292},
{"learn":[0.3010766378],"iteration":968,"passed_time":6.521748552,"remaining_time":0.2086421105},
{"learn":[0.3009623884],"iteration":969,"passed_time":6.52920399,"remaining_time":0.201934144},
{"learn":[0.3008950223],"iteration":970,"passed_time":6.535628758,"remaining_time":0.1951938558},
{"learn":[0.3008210544],"iteration":971,"passed_time":6.542485894,"remaining_time":0.1884666719},
{"learn":[0.3007831966],"iteration":972,"passed_time":6.547984552,"remaining_time":0.1817015241},
{"learn":[0.3007180893],"iteration":973,"passed_time":6.553628151,"remaining_time":0.1749428459},
{"learn":[0.3005628851],"iteration":974,"passed_time":6.560817422,"remaining_time":0.1682260877},
{"learn":[0.3004313575],"iteration":975,"passed_time":6.567346786,"remaining_time":0.1614921341},
{"learn":[0.3003357014],"iteration":976,"passed_time":6.574561176,"remaining_time":0.1547747257},
{"learn":[0.30024784],"iteration":977,"passed_time":6.580763361,"remaining_time":0.1480335316},
{"learn":[0.3002076878],"iteration":978,"passed_time":6.586788245,"remaining_time":0.1412896355},
{"learn":[0.3001271923],"iteration":979,"passed_time":6.593392133,"remaining_time":0.1345590231},
{"learn":[0.3000362256],"iteration":980,"passed_time":6.599284682,"remaining_time":0.1278148919},
{"learn":[0.2999738565],"iteration":981,"passed_time":6.607032287,"remaining_time":0.1211064981},
{"learn":[0.2998798852],"iteration":982,"passed_time":6.612736295,"remaining_time":0.114360648},
{"learn":[0.2998146618],"iteration":983,"passed_time":6.619319037,"remaining_time":0.1076312038},
{"learn":[0.2996988275],"iteration":984,"passed_time":6.625685103,"remaining_time":0.1008987579},
{"learn":[0.2996270956],"iteration":985,"passed_time":6.631020581,"remaining_time":0.09415242204},
{"learn":[0.2995488007],"iteration":986,"passed_time":6.63820269,"remaining_time":0.08743326745},
{"learn":[0.2994629765],"iteration":987,"passed_time":6.644054526,"remaining_time":0.08069701854},
{"learn":[0.2993522924],"iteration":988,"passed_time":6.650756515,"remaining_time":0.07397201382},
{"learn":[0.2992762344],"iteration":989,"passed_time":6.65688987,"remaining_time":0.06724131182},
{"learn":[0.299220695],"iteration":990,"passed_time":6.663272089,"remaining_time":0.06051407548},
{"learn":[0.2991684612],"iteration":991,"passed_time":6.67052743,"remaining_time":0.05379457605},
{"learn":[0.2990770758],"iteration":992,"passed_time":6.676910926,"remaining_time":0.04706785144},
{"learn":[0.2989920909],"iteration":993,"passed_time":6.683950668,"remaining_time":0.04034577868},
{"learn":[0.2988825295],"iteration":994,"passed_time":6.690605904,"remaining_time":0.0336211352},
{"learn":[0.2987877636],"iteration":995,"passed_time":6.69825953,"remaining_time":0.02690064068},
{"learn":[0.2987075144],"iteration":996,"passed_time":6.704322274,"remaining_time":0.02017348728},
{"learn":[0.2986521201],"iteration":997,"passed_time":6.711034481,"remaining_time":0.0134489669},
{"learn":[0.298590342],"iteration":998,"passed_time":6.717330366,"remaining_time":0.00672405442},
{"learn":[0.2985338526],"iteration":999,"passed_time":6.723295617,"remaining_time":0}
]}